Workbook
Name Slicer_Payment_Type: #N/A
Name Slicer_Quantity: #N/A

Sheet Data 
A1: Sales_ID | B1: Order_Date | C1: Customer_ID | D1: Product_ID | E1: Store_ID | F1: Quantity | G1: Unit_Price | H1: Discount | I1: Payment_Type | J1: Total_Amount
A2: SALE0 | B2: 45480 | C2: CUST1409 | D2: PROD97 | E2: STORE3 | F2: 1 | G2: 218.04 | H2: 0.09 | I2: Credit Card | J2: 198.4164
A3: SALE1 | B3: 45285 | C3: CUST1467 | D3: PROD74 | E3: STORE17 | F3: 3 | G3: 104.47 | H3: 0.27 | I3: PayPal | J3: 228.7893
A4: SALE2 | B4: 45446 | C4: CUST1056 | D4: PROD49 | E4: STORE8 | F4: 4 | G4: 914.05 | H4: 0.25 | I4: Credit Card | J4: 2742.15
A5: SALE3 | B5: 45259 | C5: CUST1346 | D5: PROD76 | E5: STORE8 | F5: 1 | G5: 921.51 | H5: 0.16 | I5: COD | J5: 774.0684
A6: SALE4 | B6: 45297 | C6: CUST1493 | D6: PROD59 | E6: STORE5 | F6: 3 | G6: 745.3 | H6: 0.18 | I6: Credit Card | J6: 1833.438
A7: SALE5 | B7: 45499 | C7: CUST1116 | D7: PROD15 | E7: STORE7 | F7: 3 | G7: 147.01 | H7: 0.19 | I7: COD | J7: 357.2343
A8: SALE6 | B8: 45850 | C8: CUST1016 | D8: PROD56 | E8: STORE4 | F8: 2 | G8: 785.31 | H8: 0.15 | I8: PayPal | J8: 1335.027
A9: SALE7 | B9: 45248 | C9: CUST1152 | D9: PROD70 | E9: STORE8 | F9: 4 | G9: 342.39 | H9: 0.23 | I9: PayPal | J9: 1054.5612
A10: SALE8 | B10: 45781 | C10: CUST1187 | D10: PROD99 | E10: STORE5 | G10: 448.25 | H10: 0.07 | I10: PayPal | J10: 1250.6175
A11: SALE9 | B11: 45869 | C11: CUST1464 | D11: PROD33 | E11: STORE0 | F11: 2 | G11: 873.17 | H11: 0.23 | I11: PayPal | J11: 1344.6818
A12: SALE10 | B12: 45335 | C12: CUST1065 | D12: PROD24 | E12: STORE14 | F12: 1 | G12: 278.63 | H12: 0.07 | I12: Credit Card | J12: 259.1259
A13: SALE11 | B13: 45801 | C13: CUST1320 | D13: PROD39 | E13: STORE1 | F13: 4 | G13: 286.92 | H13: 0.17 | I13: Credit Card | J13: 952.5744
A14: SALE12 | B14: 45528 | C14: CUST1237 | D14: PROD88 | E14: STORE4 | F14: 4 | G14: 644.58 | H14: 0.01 | I14: Credit Card | J14: 2552.5368
A15: SALE13 | B15: 45875 | C15: CUST1443 | D15: PROD34 | E15: STORE16 | F15: 2 | G15: 316.9 | H15: 0.3 | I15: PayPal | J15: 443.66
A16: SALE14 | B16: 45829 | C16: CUST1348 | D16: PROD24 | E16: STORE15 | F16: 4 | G16: 403.47 | H16: 0.29 | I16: PayPal | J16: 1145.8548
A17: SALE15 | B17: 45636 | C17: CUST1435 | D17: PROD36 | E17: STORE9 | G17: 871.34 | H17: 0.04 | I17: COD | J17: 2509.4592
A18: SALE16 | B18: 45913 | C18: CUST1276 | D18: PROD65 | E18: STORE19 | F18: 2 | G18: 451.98 | H18: 0.25 | I18: Credit Card | J18: 677.97
A19: SALE17 | B19: 45637 | C19: CUST1079 | D19: PROD27 | E19: STORE4 | F19: 2 | G19: 502.69 | H19: 0.23 | I19: Credit Card | J19: 774.1426
A20: SALE18 | B20: 45517 | C20: CUST1094 | D20: PROD39 | E20: STORE4 | F20: 2 | G20: 559.23 | H20: 0.25 | I20: COD | J20: 838.845
A21: SALE19 | B21: 45369 | C21: CUST1239 | D21: PROD60 | E21: STORE13 | F21: 4 | H21: 0.04 | I21: COD | J21: 1782.4512
A22: SALE20 | B22: 45843 | C22: CUST1144 | D22: PROD72 | E22: STORE17 | F22: 3 | G22: 986.04 | H22: 0.27 | I22: COD | J22: 2159.4276
A23: SALE21 | B23: 45447 | C23: CUST1396 | D23: PROD43 | E23: STORE18 | F23: 1 | G23: 589.56 | H23: 0.22 | I23: Credit Card | J23: 459.8568
A24: SALE22 | B24: 45394 | C24: CUST1476 | D24: PROD69 | E24: STORE10 | F24: 3 | G24: 979.42 | H24: 0.03 | I24: PayPal | J24: 2850.1122
A25: SALE23 | B25: 45466 | C25: CUST1368 | D25: PROD12 | E25: STORE8 | F25: 1 | G25: 719.28 | H25: 0.08 | I25: Credit Card | J25: 661.7376
A26: SALE24 | B26: 45908 | C26: CUST1186 | D26: PROD67 | E26: STORE6 | F26: 3 | G26: 77.6 | H26: 0.07 | I26: Credit Card | J26: 216.504
A27: SALE25 | B27: 45552 | C27: CUST1381 | D27: PROD5 | E27: STORE3 | F27: 4 | G27: 852.71 | H27: 0.14 | I27: PayPal | J27: 2933.3224
A28: SALE26 | B28: 45294 | C28: CUST1213 | D28: PROD98 | E28: STORE8 | F28: 4 | G28: 156.16 | I28: Credit Card | J28: 599.6544
A29: SALE27 | B29: 45710 | C29: CUST1200 | D29: PROD77 | E29: STORE8 | F29: 3 | G29: 815.49 | H29: 0.17 | I29: Credit Card | J29: 2030.5701
A30: SALE28 | B30: 45923 | C30: CUST1148 | D30: PROD13 | E30: STORE2 | F30: 2 | G30: 74.21 | H30: 0.11 | I30: PayPal | J30: 132.0938
A31: SALE29 | B31: 45302 | C31: CUST1348 | D31: PROD99 | E31: STORE3 | G31: 451.67 | H31: 0.15 | I31: Credit Card | J31: 1535.678
A32: SALE30 | B32: 45217 | C32: CUST1028 | D32: PROD5 | E32: STORE19 | F32: 1 | G32: 429.38 | H32: 0.13 | I32: PayPal | J32: 373.5606
A33: SALE31 | B33: 45593 | C33: CUST1412 | D33: PROD53 | E33: STORE12 | F33: 2 | G33: 148.96 | H33: 0.03 | I33: COD | J33: 288.9824
A34: SALE32 | B34: 45597 | C34: CUST1398 | D34: PROD75 | E34: STORE8 | F34: 4 | G34: 313.83 | H34: 0.08 | I34: Credit Card | J34: 1154.8944
A35: SALE33 | B35: 45620 | C35: CUST1453 | D35: PROD12 | E35: STORE6 | F35: 2 | G35: 717.31 | H35: 0.15 | I35: Credit Card | J35: 1219.427
A36: SALE34 | B36: 45215 | C36: CUST1344 | D36: PROD79 | E36: STORE1 | G36: 873.22 | H36: 0.18 | I36: Credit Card | J36: 2148.1212
A37: SALE35 | B37: 45878 | C37: CUST1218 | D37: PROD16 | E37: STORE3 | F37: 4 | G37: 109.36 | H37: 0.19 | I37: COD | J37: 354.3264
A38: SALE36 | B38: 45635 | C38: CUST1086 | D38: PROD5 | E38: STORE7 | F38: 3 | G38: 559.52 | H38: 0.16 | I38: PayPal | J38: 1409.9904
A39: SALE37 | B39: 45329 | C39: CUST1492 | D39: PROD10 | E39: STORE17 | F39: 3 | G39: 121.76 | H39: 0.27 | I39: PayPal | J39: 266.6544
A40: SALE38 | B40: 45378 | C40: CUST1189 | D40: PROD33 | E40: STORE13 | F40: 4 | G40: 735.32 | H40: 0.06 | I40: COD | J40: 2764.8032
A41: SALE39 | B41: 45264 | C41: CUST1431 | D41: PROD94 | E41: STORE3 | F41: 2 | G41: 600.73 | H41: 0.08 | I41: Credit Card | J41: 1105.3432
A42: SALE40 | B42: 45486 | C42: CUST1072 | D42: PROD26 | E42: STORE19 | F42: 2 | G42: 873.86 | H42: 0.07 | I42: COD | J42: 1625.3796
A43: SALE41 | B43: 45241 | C43: CUST1302 | D43: PROD23 | E43: STORE8 | F43: 3 | G43: 342.47 | H43: 0.08 | I43: PayPal | J43: 945.2172
A44: SALE42 | B44: 45649 | C44: CUST1335 | D44: PROD29 | E44: STORE9 | F44: 2 | G44: 915.15 | H44: 0.16 | I44: PayPal | J44: 1537.452
A45: SALE43 | B45: 45677 | C45: CUST1084 | D45: PROD33 | E45: STORE17 | G45: 863.11 | H45: 0.28 | I45: PayPal | J45: 1864.3176
A46: SALE44 | B46: 45538 | C46: CUST1203 | D46: PROD43 | E46: STORE12 | F46: 2 | G46: 209.32 | H46: 0.23 | I46: COD | J46: 322.3528
A47: SALE45 | B47: 45606 | C47: CUST1470 | D47: PROD59 | E47: STORE8 | F47: 4 | G47: 288.6 | H47: 0.09 | I47: PayPal | J47: 1050.504
A48: SALE46 | B48: 45570 | C48: CUST1070 | D48: PROD78 | E48: STORE16 | F48: 1 | G48: 418.69 | H48: 0.06 | I48: PayPal | J48: 393.5686
A49: SALE47 | B49: 45466 | C49: CUST1008 | D49: PROD30 | E49: STORE11 | F49: 1 | G49: 135.78 | H49: 0.14 | I49: PayPal | J49: 116.7708
A50: SALE48 | B50: 45218 | C50: CUST1203 | D50: PROD44 | E50: STORE17 | F50: 1 | G50: 517.13 | H50: 0.28 | I50: Credit Card | J50: 372.3336
A51: SALE49 | B51: 45607 | C51: CUST1420 | D51: PROD21 | E51: STORE16 | F51: 2 | G51: 384.66 | H51: 0.08 | I51: COD | J51: 707.7744
A52: SALE50 | B52: 45291 | C52: CUST1070 | D52: PROD52 | E52: STORE9 | F52: 3 | G52: 83.7 | H52: 0.24 | I52: PayPal | J52: 190.836
A53: SALE51 | B53: 45689 | C53: CUST1142 | D53: PROD69 | E53: STORE7 | F53: 3 | G53: 76.57 | H53: 0.26 | I53: Credit Card | J53: 169.9854
A54: SALE52 | B54: 45894 | C54: CUST1148 | D54: PROD89 | E54: STORE6 | F54: 3 | I54: Credit Card | J54: 486.0633
A55: SALE53 | B55: 45677 | C55: CUST1324 | D55: PROD20 | E55: STORE8 | F55: 1 | G55: 900.35 | H55: 0.13 | I55: COD | J55: 783.3045
A56: SALE54 | B56: 45706 | C56: CUST1095 | D56: PROD40 | E56: STORE10 | F56: 4 | G56: 428.09 | H56: 0.07 | I56: Credit Card | J56: 1592.4948
A57: SALE55 | B57: 45589 | C57: CUST1416 | D57: PROD49 | E57: STORE11 | F57: 2 | G57: 559.71 | H57: 0.3 | I57: COD | J57: 783.594
A58: SALE56 | B58: 45282 | C58: CUST1080 | D58: PROD34 | E58: STORE6 | F58: 2 | G58: 833.7 | H58: 0.06 | I58: PayPal | J58: 1567.356
A59: SALE57 | B59: 45462 | C59: CUST1467 | D59: PROD47 | E59: STORE14 | F59: 2 | G59: 680.16 | H59: 0.28 | I59: Credit Card | J59: 979.4304
A60: SALE58 | B60: 45633 | C60: CUST1404 | D60: PROD15 | E60: STORE7 | F60: 4 | G60: 733.42 | I60: PayPal | J60: 2552.3016
A61: SALE59 | B61: 45257 | C61: CUST1367 | D61: PROD89 | E61: STORE11 | F61: 1 | G61: 996.33 | H61: 0.23 | I61: PayPal | J61: 767.1741
A62: SALE60 | B62: 45854 | C62: CUST1408 | D62: PROD31 | E62: STORE10 | F62: 1 | G62: 198.83 | H62: 0.09 | I62: COD | J62: 180.9353
A63: SALE61 | B63: 45716 | C63: CUST1239 | D63: PROD19 | E63: STORE7 | F63: 1 | G63: 374.92 | H63: 0.18 | I63: PayPal | J63: 307.4344
A64: SALE62 | B64: 45515 | C64: CUST1464 | D64: PROD93 | E64: STORE16 | F64: 1 | G64: 468.94 | H64: 0.12 | I64: Credit Card | J64: 412.6672
A65: SALE63 | B65: 45927 | C65: CUST1126 | D65: PROD89 | E65: STORE12 | F65: 2 | G65: 121.37 | H65: 0.05 | I65: Credit Card | J65: 230.603
A66: SALE64 | B66: 45914 | C66: CUST1255 | D66: PROD53 | E66: STORE10 | F66: 3 | G66: 480.06 | H66: 0.01 | I66: Credit Card
A67: SALE65 | B67: 45290 | C67: CUST1162 | D67: PROD99 | E67: STORE17 | F67: 2 | G67: 856.57 | H67: 0.24 | I67: Credit Card | J67: 1301.9864
A68: SALE66 | B68: 45213 | C68: CUST1269 | D68: PROD77 | E68: STORE2 | F68: 4 | G68: 814.25 | H68: 0.18 | I68: Credit Card | J68: 2670.74
A69: SALE67 | B69: 45255 | C69: CUST1483 | D69: PROD12 | E69: STORE2 | F69: 1 | G69: 989.17 | H69: 0.2 | I69: PayPal | J69: 791.336
A70: SALE68 | B70: 45270 | C70: CUST1372 | D70: PROD72 | E70: STORE10 | F70: 4 | G70: 62.48 | H70: 0.18 | I70: Credit Card | J70: 204.9344
A71: SALE69 | B71: 45897 | C71: CUST1423 | D71: PROD13 | E71: STORE16 | F71: 4 | G71: 561.24 | H71: 0.24 | I71: Credit Card | J71: 1706.1696
A72: SALE70 | B72: 45849 | C72: CUST1058 | D72: PROD60 | E72: STORE5 | F72: 3 | G72: 92.24 | H72: 0.28 | I72: COD
A73: SALE71 | B73: 45889 | C73: CUST1168 | D73: PROD72 | E73: STORE1 | F73: 2 | G73: 668.3 | H73: 0.07 | I73: Credit Card | J73: 1243.038
A74: SALE72 | B74: 45533 | C74: CUST1409 | D74: PROD38 | E74: STORE5 | F74: 1 | G74: 553.82 | H74: 0.09 | I74: Credit Card | J74: 503.9762
A75: SALE73 | B75: 45626 | C75: CUST1037 | D75: PROD45 | E75: STORE11 | F75: 2 | G75: 556.43 | H75: 0.13 | I75: Credit Card | J75: 968.1882
A76: SALE74 | B76: 45942 | C76: CUST1273 | D76: PROD20 | E76: STORE8 | F76: 1 | G76: 184.98 | H76: 0.1 | I76: COD | J76: 166.482
A77: SALE75 | B77: 45500 | C77: CUST1035 | D77: PROD97 | E77: STORE12 | F77: 4 | G77: 700.18 | H77: 0.23 | I77: Credit Card | J77: 2156.5544
A78: SALE76 | B78: 45285 | C78: CUST1019 | D78: PROD76 | E78: STORE10 | F78: 2 | G78: 686.31 | H78: 0.25 | I78: Credit Card | J78: 1029.465
A79: SALE77 | B79: 45800 | C79: CUST1007 | D79: PROD67 | E79: STORE15 | F79: 1 | G79: 687.82 | H79: 0.27 | I79: COD | J79: 502.1086
A80: SALE78 | B80: 45609 | C80: CUST1221 | D80: PROD83 | E80: STORE8 | F80: 2 | G80: 900.55 | H80: 0.16 | I80: Credit Card | J80: 1512.924
A81: SALE79 | B81: 45268 | C81: CUST1115 | D81: PROD21 | E81: STORE2 | F81: 1 | G81: 341.17 | H81: 0.15 | I81: Credit Card | J81: 289.9945
A82: SALE80 | B82: 45885 | C82: CUST1176 | D82: PROD52 | E82: STORE8 | F82: 1 | G82: 442.27 | H82: 0.06 | I82: COD | J82: 415.7338
A83: SALE81 | B83: 45616 | C83: CUST1253 | D83: PROD71 | E83: STORE9 | F83: 1 | G83: 363.73 | H83: 0.25 | I83: PayPal | J83: 272.7975
A84: SALE82 | B84: 45518 | C84: CUST1378 | D84: PROD91 | E84: STORE17 | F84: 2 | G84: 601.33 | H84: 0.16 | I84: PayPal | J84: 1010.2344
A85: SALE83 | B85: 45427 | C85: CUST1403 | D85: PROD17 | E85: STORE18 | F85: 4 | G85: 34.39 | H85: 0.03 | I85: PayPal | J85: 133.4332
A86: SALE84 | B86: 45268 | C86: CUST1423 | D86: PROD46 | E86: STORE17 | F86: 1 | G86: 773.57 | H86: 0.05 | I86: COD
A87: SALE85 | B87: 45282 | C87: CUST1054 | D87: PROD88 | E87: STORE7 | F87: 4 | G87: 127.1 | H87: 0.24 | I87: COD | J87: 386.384
A88: SALE86 | B88: 45545 | C88: CUST1303 | D88: PROD20 | E88: STORE3 | F88: 3 | G88: 899.58 | H88: 0.28 | I88: PayPal | J88: 1943.0928
A89: SALE87 | B89: 45755 | C89: CUST1327 | D89: PROD1 | E89: STORE10 | F89: 3 | G89: 964.39 | H89: 0.04 | I89: Credit Card | J89: 2777.4432
A90: SALE88 | B90: 45588 | C90: CUST1183 | D90: PROD38 | E90: STORE0 | F90: 2 | G90: 217.83 | H90: 0.14 | I90: PayPal | J90: 374.6676
A91: SALE89 | B91: 45848 | C91: CUST1143 | D91: PROD17 | E91: STORE1 | F91: 4 | G91: 187.71 | H91: 0.06 | I91: COD | J91: 705.7896
A92: SALE90 | B92: 45577 | C92: CUST1010 | D92: PROD33 | E92: STORE18 | F92: 2 | G92: 350.12 | H92: 0.12 | I92: COD | J92: 616.2112
A93: SALE91 | B93: 45312 | C93: CUST1406 | D93: PROD16 | E93: STORE1 | F93: 4 | G93: 102.19 | H93: 0.17 | I93: PayPal | J93: 339.2708
A94: SALE92 | B94: 45350 | C94: CUST1007 | D94: PROD86 | E94: STORE4 | F94: 1 | G94: 696.53 | H94: 0.17 | I94: Credit Card | J94: 578.1199
A95: SALE93 | B95: 45657 | C95: CUST1065 | D95: PROD19 | E95: STORE4 | F95: 2 | G95: 327.52 | H95: 0.15 | I95: PayPal | J95: 556.784
A96: SALE94 | B96: 45530 | C96: CUST1298 | D96: PROD97 | E96: STORE19 | F96: 2 | G96: 569.36 | H96: 0.01 | I96: PayPal
A97: SALE95 | B97: 45556 | C97: CUST1321 | D97: PROD99 | E97: STORE6 | F97: 2 | G97: 68.29 | H97: 0.14 | I97: COD | J97: 117.4588
A98: SALE96 | B98: 45523 | C98: CUST1244 | D98: PROD50 | E98: STORE10 | F98: 1 | G98: 842.9 | H98: 0.06 | I98: COD | J98: 792.326
A99: SALE97 | B99: 45587 | C99: CUST1287 | D99: PROD3 | E99: STORE3 | F99: 3 | G99: 751.94 | H99: 0.26 | I99: PayPal | J99: 1669.3068
A100: SALE98 | B100: 45580 | C100: CUST1131 | D100: PROD56 | E100: STORE7 | F100: 4 | G100: 476.28 | H100: 0.17 | I100: Credit Card | J100: 1581.2496
...

Sheet Data cleaning
A1: 2 | B1: find/remove duplicates - No duplicate | J1: validate data | K1: handle missing/inconsistent data
A3: Sales_ID | B3: Order_Date | C3: Customer_ID | D3: Product_ID | E3: Store_ID | F3: Quantity | G3: Unit_Price | H3: Discount | I3: Payment_Type | J3: Total_Amount | L3: {=TRIM(Table14[#All])} -> Sales_ID | M3: Order_Date | N3: Customer_ID | O3: Product_ID | P3: Store_ID | Q3: Quantity | R3: Unit_Price | S3: Discount | T3: Payment_Type | U3: Total_Amount | W3: {=PROPER(L3:U2003)} -> Sales_Id | X3: Order_Date | Y3: Customer_Id | Z3: Product_Id | AA3: Store_Id | AB3: Quantity | AC3: Unit_Price | AD3: Discount | AE3: Payment_Type | AF3: Total_Amount
A4: SALE0 | B4: 45480 | C4: CUST1409 | D4: PROD97 | E4: STORE3 | F4: 1 | G4: 218.04 | H4: 0.09 | I4: Credit Card | J4: 198.4164 | L4: SALE0 | M4: 45480 | N4: CUST1409 | O4: PROD97 | P4: STORE3 | Q4: 1 | R4: 218.04 | S4: 0.09 | T4: Credit Card | U4: 198.4164 | W4: Sale0 | X4: 45480 | Y4: Cust1409 | Z4: Prod97 | AA4: Store3 | AB4: 1 | AC4: 218.04 | AD4: 0.09 | AE4: Credit Card | AF4: 198.4164
A5: SALE1 | B5: 45285 | C5: CUST1467 | D5: PROD74 | E5: STORE17 | F5: 3 | G5: 104.47 | H5: 0.27 | I5: PayPal | J5: 228.7893 | L5: SALE1 | M5: 45285 | N5: CUST1467 | O5: PROD74 | P5: STORE17 | Q5: 3 | R5: 104.47 | S5: 0.27 | T5: PayPal | U5: 228.7893 | W5: Sale1 | X5: 45285 | Y5: Cust1467 | Z5: Prod74 | AA5: Store17 | AB5: 3 | AC5: 104.47 | AD5: 0.27 | AE5: Paypal | AF5: 228.7893
A6: SALE2 | B6: 45446 | C6: CUST1056 | D6: PROD49 | E6: STORE8 | F6: 4 | G6: 914.05 | H6: 0.25 | I6: Credit Card | J6: 2742.15 | L6: SALE2 | M6: 45446 | N6: CUST1056 | O6: PROD49 | P6: STORE8 | Q6: 4 | R6: 914.05 | S6: 0.25 | T6: Credit Card | U6: 2742.15 | W6: Sale2 | X6: 45446 | Y6: Cust1056 | Z6: Prod49 | AA6: Store8 | AB6: 4 | AC6: 914.05 | AD6: 0.25 | AE6: Credit Card | AF6: 2742.15
A7: SALE3 | B7: 45259 | C7: CUST1346 | D7: PROD76 | E7: STORE8 | F7: 1 | G7: 921.51 | H7: 0.16 | I7: COD | J7: 774.0684 | L7: SALE3 | M7: 45259 | N7: CUST1346 | O7: PROD76 | P7: STORE8 | Q7: 1 | R7: 921.51 | S7: 0.16 | T7: COD | U7: 774.0684 | W7: Sale3 | X7: 45259 | Y7: Cust1346 | Z7: Prod76 | AA7: Store8 | AB7: 1 | AC7: 921.51 | AD7: 0.16 | AE7: Cod | AF7: 774.0684
A8: SALE4 | B8: 45297 | C8: CUST1493 | D8: PROD59 | E8: STORE5 | F8: 3 | G8: 745.3 | H8: 0.18 | I8: Credit Card | J8: 1833.438 | L8: SALE4 | M8: 45297 | N8: CUST1493 | O8: PROD59 | P8: STORE5 | Q8: 3 | R8: 745.3 | S8: 0.18 | T8: Credit Card | U8: 1833.438 | W8: Sale4 | X8: 45297 | Y8: Cust1493 | Z8: Prod59 | AA8: Store5 | AB8: 3 | AC8: 745.3 | AD8: 0.18 | AE8: Credit Card | AF8: 1833.438
A9: SALE5 | B9: 45499 | C9: CUST1116 | D9: PROD15 | E9: STORE7 | F9: 3 | G9: 147.01 | H9: 0.19 | I9: COD | J9: 357.2343 | L9: SALE5 | M9: 45499 | N9: CUST1116 | O9: PROD15 | P9: STORE7 | Q9: 3 | R9: 147.01 | S9: 0.19 | T9: COD | U9: 357.2343 | W9: Sale5 | X9: 45499 | Y9: Cust1116 | Z9: Prod15 | AA9: Store7 | AB9: 3 | AC9: 147.01 | AD9: 0.19 | AE9: Cod | AF9: 357.2343
A10: SALE6 | B10: 45850 | C10: CUST1016 | D10: PROD56 | E10: STORE4 | F10: 2 | G10: 785.31 | H10: 0.15 | I10: PayPal | J10: 1335.027 | L10: SALE6 | M10: 45850 | N10: CUST1016 | O10: PROD56 | P10: STORE4 | Q10: 2 | R10: 785.31 | S10: 0.15 | T10: PayPal | U10: 1335.027 | W10: Sale6 | X10: 45850 | Y10: Cust1016 | Z10: Prod56 | AA10: Store4 | AB10: 2 | AC10: 785.31 | AD10: 0.15 | AE10: Paypal | AF10: 1335.027
A11: SALE7 | B11: 45248 | C11: CUST1152 | D11: PROD70 | E11: STORE8 | F11: 4 | G11: 342.39 | H11: 0.23 | I11: PayPal | J11: 1054.5612 | L11: SALE7 | M11: 45248 | N11: CUST1152 | O11: PROD70 | P11: STORE8 | Q11: 4 | R11: 342.39 | S11: 0.23 | T11: PayPal | U11: 1054.5612 | W11: Sale7 | X11: 45248 | Y11: Cust1152 | Z11: Prod70 | AA11: Store8 | AB11: 4 | AC11: 342.39 | AD11: 0.23 | AE11: Paypal | AF11: 1054.5612
A12: SALE8 | B12: 45781 | C12: CUST1187 | D12: PROD99 | E12: STORE5 | G12: 448.25 | H12: 0.07 | I12: PayPal | J12: 1250.6175 | L12: SALE8 | M12: 45781 | N12: CUST1187 | O12: PROD99 | P12: STORE5 | R12: 448.25 | S12: 0.07 | T12: PayPal | U12: 1250.6175 | W12: Sale8 | X12: 45781 | Y12: Cust1187 | Z12: Prod99 | AA12: Store5 | AC12: 448.25 | AD12: 0.07 | AE12: Paypal | AF12: 1250.6175
A13: SALE9 | B13: 45869 | C13: CUST1464 | D13: PROD33 | E13: STORE0 | F13: 2 | G13: 873.17 | H13: 0.23 | I13: PayPal | J13: 1344.6818 | L13: SALE9 | M13: 45869 | N13: CUST1464 | O13: PROD33 | P13: STORE0 | Q13: 2 | R13: 873.17 | S13: 0.23 | T13: PayPal | U13: 1344.6818 | W13: Sale9 | X13: 45869 | Y13: Cust1464 | Z13: Prod33 | AA13: Store0 | AB13: 2 | AC13: 873.17 | AD13: 0.23 | AE13: Paypal | AF13: 1344.6818
A14: SALE10 | B14: 45335 | C14: CUST1065 | D14: PROD24 | E14: STORE14 | F14: 1 | G14: 278.63 | H14: 0.07 | I14: Credit Card | J14: 259.1259 | L14: SALE10 | M14: 45335 | N14: CUST1065 | O14: PROD24 | P14: STORE14 | Q14: 1 | R14: 278.63 | S14: 0.07 | T14: Credit Card | U14: 259.1259 | W14: Sale10 | X14: 45335 | Y14: Cust1065 | Z14: Prod24 | AA14: Store14 | AB14: 1 | AC14: 278.63 | AD14: 0.07 | AE14: Credit Card | AF14: 259.1259
A15: SALE11 | B15: 45801 | C15: CUST1320 | D15: PROD39 | E15: STORE1 | F15: 4 | G15: 286.92 | H15: 0.17 | I15: Credit Card | J15: 952.5744 | L15: SALE11 | M15: 45801 | N15: CUST1320 | O15: PROD39 | P15: STORE1 | Q15: 4 | R15: 286.92 | S15: 0.17 | T15: Credit Card | U15: 952.5744 | W15: Sale11 | X15: 45801 | Y15: Cust1320 | Z15: Prod39 | AA15: Store1 | AB15: 4 | AC15: 286.92 | AD15: 0.17 | AE15: Credit Card | AF15: 952.5744
A16: SALE12 | B16: 45528 | C16: CUST1237 | D16: PROD88 | E16: STORE4 | F16: 4 | G16: 644.58 | H16: 0.01 | I16: Credit Card | J16: 2552.5368 | L16: SALE12 | M16: 45528 | N16: CUST1237 | O16: PROD88 | P16: STORE4 | Q16: 4 | R16: 644.58 | S16: 0.01 | T16: Credit Card | U16: 2552.5368 | W16: Sale12 | X16: 45528 | Y16: Cust1237 | Z16: Prod88 | AA16: Store4 | AB16: 4 | AC16: 644.58 | AD16: 0.01 | AE16: Credit Card | AF16: 2552.5368
A17: SALE13 | B17: 45875 | C17: CUST1443 | D17: PROD34 | E17: STORE16 | F17: 2 | G17: 316.9 | H17: 0.3 | I17: PayPal | J17: 443.66 | L17: SALE13 | M17: 45875 | N17: CUST1443 | O17: PROD34 | P17: STORE16 | Q17: 2 | R17: 316.9 | S17: 0.3 | T17: PayPal | U17: 443.66 | W17: Sale13 | X17: 45875 | Y17: Cust1443 | Z17: Prod34 | AA17: Store16 | AB17: 2 | AC17: 316.9 | AD17: 0.3 | AE17: Paypal | AF17: 443.66
A18: SALE14 | B18: 45829 | C18: CUST1348 | D18: PROD24 | E18: STORE15 | F18: 4 | G18: 403.47 | H18: 0.29 | I18: PayPal | J18: 1145.8548 | L18: SALE14 | M18: 45829 | N18: CUST1348 | O18: PROD24 | P18: STORE15 | Q18: 4 | R18: 403.47 | S18: 0.29 | T18: PayPal | U18: 1145.8548 | W18: Sale14 | X18: 45829 | Y18: Cust1348 | Z18: Prod24 | AA18: Store15 | AB18: 4 | AC18: 403.47 | AD18: 0.29 | AE18: Paypal | AF18: 1145.8548
A19: SALE15 | B19: 45636 | C19: CUST1435 | D19: PROD36 | E19: STORE9 | G19: 871.34 | H19: 0.04 | I19: COD | J19: 2509.4592 | L19: SALE15 | M19: 45636 | N19: CUST1435 | O19: PROD36 | P19: STORE9 | R19: 871.34 | S19: 0.04 | T19: COD | U19: 2509.4592 | W19: Sale15 | X19: 45636 | Y19: Cust1435 | Z19: Prod36 | AA19: Store9 | AC19: 871.34 | AD19: 0.04 | AE19: Cod | AF19: 2509.4592
A20: SALE16 | B20: 45913 | C20: CUST1276 | D20: PROD65 | E20: STORE19 | F20: 2 | G20: 451.98 | H20: 0.25 | I20: Credit Card | J20: 677.97 | L20: SALE16 | M20: 45913 | N20: CUST1276 | O20: PROD65 | P20: STORE19 | Q20: 2 | R20: 451.98 | S20: 0.25 | T20: Credit Card | U20: 677.97 | W20: Sale16 | X20: 45913 | Y20: Cust1276 | Z20: Prod65 | AA20: Store19 | AB20: 2 | AC20: 451.98 | AD20: 0.25 | AE20: Credit Card | AF20: 677.97
A21: SALE17 | B21: 45637 | C21: CUST1079 | D21: PROD27 | E21: STORE4 | F21: 2 | G21: 502.69 | H21: 0.23 | I21: Credit Card | J21: 774.1426 | L21: SALE17 | M21: 45637 | N21: CUST1079 | O21: PROD27 | P21: STORE4 | Q21: 2 | R21: 502.69 | S21: 0.23 | T21: Credit Card | U21: 774.1426 | W21: Sale17 | X21: 45637 | Y21: Cust1079 | Z21: Prod27 | AA21: Store4 | AB21: 2 | AC21: 502.69 | AD21: 0.23 | AE21: Credit Card | AF21: 774.1426
A22: SALE18 | B22: 45517 | C22: CUST1094 | D22: PROD39 | E22: STORE4 | F22: 2 | G22: 559.23 | H22: 0.25 | I22: COD | J22: 838.845 | L22: SALE18 | M22: 45517 | N22: CUST1094 | O22: PROD39 | P22: STORE4 | Q22: 2 | R22: 559.23 | S22: 0.25 | T22: COD | U22: 838.845 | W22: Sale18 | X22: 45517 | Y22: Cust1094 | Z22: Prod39 | AA22: Store4 | AB22: 2 | AC22: 559.23 | AD22: 0.25 | AE22: Cod | AF22: 838.845
A23: SALE19 | B23: 45369 | C23: CUST1239 | D23: PROD60 | E23: STORE13 | F23: 4 | H23: 0.04 | I23: COD | J23: 1782.4512 | L23: SALE19 | M23: 45369 | N23: CUST1239 | O23: PROD60 | P23: STORE13 | Q23: 4 | S23: 0.04 | T23: COD | U23: 1782.4512 | W23: Sale19 | X23: 45369 | Y23: Cust1239 | Z23: Prod60 | AA23: Store13 | AB23: 4 | AD23: 0.04 | AE23: Cod | AF23: 1782.4512
A24: SALE20 | B24: 45843 | C24: CUST1144 | D24: PROD72 | E24: STORE17 | F24: 3 | G24: 986.04 | H24: 0.27 | I24: COD | J24: 2159.4276 | L24: SALE20 | M24: 45843 | N24: CUST1144 | O24: PROD72 | P24: STORE17 | Q24: 3 | R24: 986.04 | S24: 0.27 | T24: COD | U24: 2159.4276 | W24: Sale20 | X24: 45843 | Y24: Cust1144 | Z24: Prod72 | AA24: Store17 | AB24: 3 | AC24: 986.04 | AD24: 0.27 | AE24: Cod | AF24: 2159.4276
A25: SALE21 | B25: 45447 | C25: CUST1396 | D25: PROD43 | E25: STORE18 | F25: 1 | G25: 589.56 | H25: 0.22 | I25: Credit Card | J25: 459.8568 | L25: SALE21 | M25: 45447 | N25: CUST1396 | O25: PROD43 | P25: STORE18 | Q25: 1 | R25: 589.56 | S25: 0.22 | T25: Credit Card | U25: 459.8568 | W25: Sale21 | X25: 45447 | Y25: Cust1396 | Z25: Prod43 | AA25: Store18 | AB25: 1 | AC25: 589.56 | AD25: 0.22 | AE25: Credit Card | AF25: 459.8568
A26: SALE22 | B26: 45394 | C26: CUST1476 | D26: PROD69 | E26: STORE10 | F26: 3 | G26: 979.42 | H26: 0.03 | I26: PayPal | J26: 2850.1122 | L26: SALE22 | M26: 45394 | N26: CUST1476 | O26: PROD69 | P26: STORE10 | Q26: 3 | R26: 979.42 | S26: 0.03 | T26: PayPal | U26: 2850.1122 | W26: Sale22 | X26: 45394 | Y26: Cust1476 | Z26: Prod69 | AA26: Store10 | AB26: 3 | AC26: 979.42 | AD26: 0.03 | AE26: Paypal | AF26: 2850.1122
A27: SALE23 | B27: 45466 | C27: CUST1368 | D27: PROD12 | E27: STORE8 | F27: 1 | G27: 719.28 | H27: 0.08 | I27: Credit Card | J27: 661.7376 | L27: SALE23 | M27: 45466 | N27: CUST1368 | O27: PROD12 | P27: STORE8 | Q27: 1 | R27: 719.28 | S27: 0.08 | T27: Credit Card | U27: 661.7376 | W27: Sale23 | X27: 45466 | Y27: Cust1368 | Z27: Prod12 | AA27: Store8 | AB27: 1 | AC27: 719.28 | AD27: 0.08 | AE27: Credit Card | AF27: 661.7376
A28: SALE24 | B28: 45908 | C28: CUST1186 | D28: PROD67 | E28: STORE6 | F28: 3 | G28: 77.6 | H28: 0.07 | I28: Credit Card | J28: 216.504 | L28: SALE24 | M28: 45908 | N28: CUST1186 | O28: PROD67 | P28: STORE6 | Q28: 3 | R28: 77.6 | S28: 0.07 | T28: Credit Card | U28: 216.504 | W28: Sale24 | X28: 45908 | Y28: Cust1186 | Z28: Prod67 | AA28: Store6 | AB28: 3 | AC28: 77.6 | AD28: 0.07 | AE28: Credit Card | AF28: 216.504
A29: SALE25 | B29: 45552 | C29: CUST1381 | D29: PROD5 | E29: STORE3 | F29: 4 | G29: 852.71 | H29: 0.14 | I29: PayPal | J29: 2933.3224 | L29: SALE25 | M29: 45552 | N29: CUST1381 | O29: PROD5 | P29: STORE3 | Q29: 4 | R29: 852.71 | S29: 0.14 | T29: PayPal | U29: 2933.3224 | W29: Sale25 | X29: 45552 | Y29: Cust1381 | Z29: Prod5 | AA29: Store3 | AB29: 4 | AC29: 852.71 | AD29: 0.14 | AE29: Paypal | AF29: 2933.3224
A30: SALE26 | B30: 45294 | C30: CUST1213 | D30: PROD98 | E30: STORE8 | F30: 4 | G30: 156.16 | I30: Credit Card | J30: 599.6544 | L30: SALE26 | M30: 45294 | N30: CUST1213 | O30: PROD98 | P30: STORE8 | Q30: 4 | R30: 156.16 | T30: Credit Card | U30: 599.6544 | W30: Sale26 | X30: 45294 | Y30: Cust1213 | Z30: Prod98 | AA30: Store8 | AB30: 4 | AC30: 156.16 | AE30: Credit Card | AF30: 599.6544
A31: SALE27 | B31: 45710 | C31: CUST1200 | D31: PROD77 | E31: STORE8 | F31: 3 | G31: 815.49 | H31: 0.17 | I31: Credit Card | J31: 2030.5701 | L31: SALE27 | M31: 45710 | N31: CUST1200 | O31: PROD77 | P31: STORE8 | Q31: 3 | R31: 815.49 | S31: 0.17 | T31: Credit Card | U31: 2030.5701 | W31: Sale27 | X31: 45710 | Y31: Cust1200 | Z31: Prod77 | AA31: Store8 | AB31: 3 | AC31: 815.49 | AD31: 0.17 | AE31: Credit Card | AF31: 2030.5701
A32: SALE28 | B32: 45923 | C32: CUST1148 | D32: PROD13 | E32: STORE2 | F32: 2 | G32: 74.21 | H32: 0.11 | I32: PayPal | J32: 132.0938 | L32: SALE28 | M32: 45923 | N32: CUST1148 | O32: PROD13 | P32: STORE2 | Q32: 2 | R32: 74.21 | S32: 0.11 | T32: PayPal | U32: 132.0938 | W32: Sale28 | X32: 45923 | Y32: Cust1148 | Z32: Prod13 | AA32: Store2 | AB32: 2 | AC32: 74.21 | AD32: 0.11 | AE32: Paypal | AF32: 132.0938
A33: SALE29 | B33: 45302 | C33: CUST1348 | D33: PROD99 | E33: STORE3 | G33: 451.67 | H33: 0.15 | I33: Credit Card | J33: 1535.678 | L33: SALE29 | M33: 45302 | N33: CUST1348 | O33: PROD99 | P33: STORE3 | R33: 451.67 | S33: 0.15 | T33: Credit Card | U33: 1535.678 | W33: Sale29 | X33: 45302 | Y33: Cust1348 | Z33: Prod99 | AA33: Store3 | AC33: 451.67 | AD33: 0.15 | AE33: Credit Card | AF33: 1535.678
A34: SALE30 | B34: 45217 | C34: CUST1028 | D34: PROD5 | E34: STORE19 | F34: 1 | G34: 429.38 | H34: 0.13 | I34: PayPal | J34: 373.5606 | L34: SALE30 | M34: 45217 | N34: CUST1028 | O34: PROD5 | P34: STORE19 | Q34: 1 | R34: 429.38 | S34: 0.13 | T34: PayPal | U34: 373.5606 | W34: Sale30 | X34: 45217 | Y34: Cust1028 | Z34: Prod5 | AA34: Store19 | AB34: 1 | AC34: 429.38 | AD34: 0.13 | AE34: Paypal | AF34: 373.5606
A35: SALE31 | B35: 45593 | C35: CUST1412 | D35: PROD53 | E35: STORE12 | F35: 2 | G35: 148.96 | H35: 0.03 | I35: COD | J35: 288.9824 | L35: SALE31 | M35: 45593 | N35: CUST1412 | O35: PROD53 | P35: STORE12 | Q35: 2 | R35: 148.96 | S35: 0.03 | T35: COD | U35: 288.9824 | W35: Sale31 | X35: 45593 | Y35: Cust1412 | Z35: Prod53 | AA35: Store12 | AB35: 2 | AC35: 148.96 | AD35: 0.03 | AE35: Cod | AF35: 288.9824
A36: SALE32 | B36: 45597 | C36: CUST1398 | D36: PROD75 | E36: STORE8 | F36: 4 | G36: 313.83 | H36: 0.08 | I36: Credit Card | J36: 1154.8944 | L36: SALE32 | M36: 45597 | N36: CUST1398 | O36: PROD75 | P36: STORE8 | Q36: 4 | R36: 313.83 | S36: 0.08 | T36: Credit Card | U36: 1154.8944 | W36: Sale32 | X36: 45597 | Y36: Cust1398 | Z36: Prod75 | AA36: Store8 | AB36: 4 | AC36: 313.83 | AD36: 0.08 | AE36: Credit Card | AF36: 1154.8944
A37: SALE33 | B37: 45620 | C37: CUST1453 | D37: PROD12 | E37: STORE6 | F37: 2 | G37: 717.31 | H37: 0.15 | I37: Credit Card | J37: 1219.427 | L37: SALE33 | M37: 45620 | N37: CUST1453 | O37: PROD12 | P37: STORE6 | Q37: 2 | R37: 717.31 | S37: 0.15 | T37: Credit Card | U37: 1219.427 | W37: Sale33 | X37: 45620 | Y37: Cust1453 | Z37: Prod12 | AA37: Store6 | AB37: 2 | AC37: 717.31 | AD37: 0.15 | AE37: Credit Card | AF37: 1219.427
A38: SALE34 | B38: 45215 | C38: CUST1344 | D38: PROD79 | E38: STORE1 | G38: 873.22 | H38: 0.18 | I38: Credit Card | J38: 2148.1212 | L38: SALE34 | M38: 45215 | N38: CUST1344 | O38: PROD79 | P38: STORE1 | R38: 873.22 | S38: 0.18 | T38: Credit Card | U38: 2148.1212 | W38: Sale34 | X38: 45215 | Y38: Cust1344 | Z38: Prod79 | AA38: Store1 | AC38: 873.22 | AD38: 0.18 | AE38: Credit Card | AF38: 2148.1212
A39: SALE35 | B39: 45878 | C39: CUST1218 | D39: PROD16 | E39: STORE3 | F39: 4 | G39: 109.36 | H39: 0.19 | I39: COD | J39: 354.3264 | L39: SALE35 | M39: 45878 | N39: CUST1218 | O39: PROD16 | P39: STORE3 | Q39: 4 | R39: 109.36 | S39: 0.19 | T39: COD | U39: 354.3264 | W39: Sale35 | X39: 45878 | Y39: Cust1218 | Z39: Prod16 | AA39: Store3 | AB39: 4 | AC39: 109.36 | AD39: 0.19 | AE39: Cod | AF39: 354.3264
A40: SALE36 | B40: 45635 | C40: CUST1086 | D40: PROD5 | E40: STORE7 | F40: 3 | G40: 559.52 | H40: 0.16 | I40: PayPal | J40: 1409.9904 | L40: SALE36 | M40: 45635 | N40: CUST1086 | O40: PROD5 | P40: STORE7 | Q40: 3 | R40: 559.52 | S40: 0.16 | T40: PayPal | U40: 1409.9904 | W40: Sale36 | X40: 45635 | Y40: Cust1086 | Z40: Prod5 | AA40: Store7 | AB40: 3 | AC40: 559.52 | AD40: 0.16 | AE40: Paypal | AF40: 1409.9904
A41: SALE37 | B41: 45329 | C41: CUST1492 | D41: PROD10 | E41: STORE17 | F41: 3 | G41: 121.76 | H41: 0.27 | I41: PayPal | J41: 266.6544 | L41: SALE37 | M41: 45329 | N41: CUST1492 | O41: PROD10 | P41: STORE17 | Q41: 3 | R41: 121.76 | S41: 0.27 | T41: PayPal | U41: 266.6544 | W41: Sale37 | X41: 45329 | Y41: Cust1492 | Z41: Prod10 | AA41: Store17 | AB41: 3 | AC41: 121.76 | AD41: 0.27 | AE41: Paypal | AF41: 266.6544
A42: SALE38 | B42: 45378 | C42: CUST1189 | D42: PROD33 | E42: STORE13 | F42: 4 | G42: 735.32 | H42: 0.06 | I42: COD | J42: 2764.8032 | L42: SALE38 | M42: 45378 | N42: CUST1189 | O42: PROD33 | P42: STORE13 | Q42: 4 | R42: 735.32 | S42: 0.06 | T42: COD | U42: 2764.8032 | W42: Sale38 | X42: 45378 | Y42: Cust1189 | Z42: Prod33 | AA42: Store13 | AB42: 4 | AC42: 735.32 | AD42: 0.06 | AE42: Cod | AF42: 2764.8032
A43: SALE39 | B43: 45264 | C43: CUST1431 | D43: PROD94 | E43: STORE3 | F43: 2 | G43: 600.73 | H43: 0.08 | I43: Credit Card | J43: 1105.3432 | L43: SALE39 | M43: 45264 | N43: CUST1431 | O43: PROD94 | P43: STORE3 | Q43: 2 | R43: 600.73 | S43: 0.08 | T43: Credit Card | U43: 1105.3432 | W43: Sale39 | X43: 45264 | Y43: Cust1431 | Z43: Prod94 | AA43: Store3 | AB43: 2 | AC43: 600.73 | AD43: 0.08 | AE43: Credit Card | AF43: 1105.3432
A44: SALE40 | B44: 45486 | C44: CUST1072 | D44: PROD26 | E44: STORE19 | F44: 2 | G44: 873.86 | H44: 0.07 | I44: COD | J44: 1625.3796 | L44: SALE40 | M44: 45486 | N44: CUST1072 | O44: PROD26 | P44: STORE19 | Q44: 2 | R44: 873.86 | S44: 0.07 | T44: COD | U44: 1625.3796 | W44: Sale40 | X44: 45486 | Y44: Cust1072 | Z44: Prod26 | AA44: Store19 | AB44: 2 | AC44: 873.86 | AD44: 0.07 | AE44: Cod | AF44: 1625.3796
A45: SALE41 | B45: 45241 | C45: CUST1302 | D45: PROD23 | E45: STORE8 | F45: 3 | G45: 342.47 | H45: 0.08 | I45: PayPal | J45: 945.2172 | L45: SALE41 | M45: 45241 | N45: CUST1302 | O45: PROD23 | P45: STORE8 | Q45: 3 | R45: 342.47 | S45: 0.08 | T45: PayPal | U45: 945.2172 | W45: Sale41 | X45: 45241 | Y45: Cust1302 | Z45: Prod23 | AA45: Store8 | AB45: 3 | AC45: 342.47 | AD45: 0.08 | AE45: Paypal | AF45: 945.2172
A46: SALE42 | B46: 45649 | C46: CUST1335 | D46: PROD29 | E46: STORE9 | F46: 2 | G46: 915.15 | H46: 0.16 | I46: PayPal | J46: 1537.452 | L46: SALE42 | M46: 45649 | N46: CUST1335 | O46: PROD29 | P46: STORE9 | Q46: 2 | R46: 915.15 | S46: 0.16 | T46: PayPal | U46: 1537.452 | W46: Sale42 | X46: 45649 | Y46: Cust1335 | Z46: Prod29 | AA46: Store9 | AB46: 2 | AC46: 915.15 | AD46: 0.16 | AE46: Paypal | AF46: 1537.452
A47: SALE43 | B47: 45677 | C47: CUST1084 | D47: PROD33 | E47: STORE17 | G47: 863.11 | H47: 0.28 | I47: PayPal | J47: 1864.3176 | L47: SALE43 | M47: 45677 | N47: CUST1084 | O47: PROD33 | P47: STORE17 | R47: 863.11 | S47: 0.28 | T47: PayPal | U47: 1864.3176 | W47: Sale43 | X47: 45677 | Y47: Cust1084 | Z47: Prod33 | AA47: Store17 | AC47: 863.11 | AD47: 0.28 | AE47: Paypal | AF47: 1864.3176
A48: SALE44 | B48: 45538 | C48: CUST1203 | D48: PROD43 | E48: STORE12 | F48: 2 | G48: 209.32 | H48: 0.23 | I48: COD | J48: 322.3528 | L48: SALE44 | M48: 45538 | N48: CUST1203 | O48: PROD43 | P48: STORE12 | Q48: 2 | R48: 209.32 | S48: 0.23 | T48: COD | U48: 322.3528 | W48: Sale44 | X48: 45538 | Y48: Cust1203 | Z48: Prod43 | AA48: Store12 | AB48: 2 | AC48: 209.32 | AD48: 0.23 | AE48: Cod | AF48: 322.3528
A49: SALE45 | B49: 45606 | C49: CUST1470 | D49: PROD59 | E49: STORE8 | F49: 4 | G49: 288.6 | H49: 0.09 | I49: PayPal | J49: 1050.504 | L49: SALE45 | M49: 45606 | N49: CUST1470 | O49: PROD59 | P49: STORE8 | Q49: 4 | R49: 288.6 | S49: 0.09 | T49: PayPal | U49: 1050.504 | W49: Sale45 | X49: 45606 | Y49: Cust1470 | Z49: Prod59 | AA49: Store8 | AB49: 4 | AC49: 288.6 | AD49: 0.09 | AE49: Paypal | AF49: 1050.504
A50: SALE46 | B50: 45570 | C50: CUST1070 | D50: PROD78 | E50: STORE16 | F50: 1 | G50: 418.69 | H50: 0.06 | I50: PayPal | J50: 393.5686 | L50: SALE46 | M50: 45570 | N50: CUST1070 | O50: PROD78 | P50: STORE16 | Q50: 1 | R50: 418.69 | S50: 0.06 | T50: PayPal | U50: 393.5686 | W50: Sale46 | X50: 45570 | Y50: Cust1070 | Z50: Prod78 | AA50: Store16 | AB50: 1 | AC50: 418.69 | AD50: 0.06 | AE50: Paypal | AF50: 393.5686
A51: SALE47 | B51: 45466 | C51: CUST1008 | D51: PROD30 | E51: STORE11 | F51: 1 | G51: 135.78 | H51: 0.14 | I51: PayPal | J51: 116.7708 | L51: SALE47 | M51: 45466 | N51: CUST1008 | O51: PROD30 | P51: STORE11 | Q51: 1 | R51: 135.78 | S51: 0.14 | T51: PayPal | U51: 116.7708 | W51: Sale47 | X51: 45466 | Y51: Cust1008 | Z51: Prod30 | AA51: Store11 | AB51: 1 | AC51: 135.78 | AD51: 0.14 | AE51: Paypal | AF51: 116.7708
A52: SALE48 | B52: 45218 | C52: CUST1203 | D52: PROD44 | E52: STORE17 | F52: 1 | G52: 517.13 | H52: 0.28 | I52: Credit Card | J52: 372.3336 | L52: SALE48 | M52: 45218 | N52: CUST1203 | O52: PROD44 | P52: STORE17 | Q52: 1 | R52: 517.13 | S52: 0.28 | T52: Credit Card | U52: 372.3336 | W52: Sale48 | X52: 45218 | Y52: Cust1203 | Z52: Prod44 | AA52: Store17 | AB52: 1 | AC52: 517.13 | AD52: 0.28 | AE52: Credit Card | AF52: 372.3336
A53: SALE49 | B53: 45607 | C53: CUST1420 | D53: PROD21 | E53: STORE16 | F53: 2 | G53: 384.66 | H53: 0.08 | I53: COD | J53: 707.7744 | L53: SALE49 | M53: 45607 | N53: CUST1420 | O53: PROD21 | P53: STORE16 | Q53: 2 | R53: 384.66 | S53: 0.08 | T53: COD | U53: 707.7744 | W53: Sale49 | X53: 45607 | Y53: Cust1420 | Z53: Prod21 | AA53: Store16 | AB53: 2 | AC53: 384.66 | AD53: 0.08 | AE53: Cod | AF53: 707.7744
A54: SALE50 | B54: 45291 | C54: CUST1070 | D54: PROD52 | E54: STORE9 | F54: 3 | G54: 83.7 | H54: 0.24 | I54: PayPal | J54: 190.836 | L54: SALE50 | M54: 45291 | N54: CUST1070 | O54: PROD52 | P54: STORE9 | Q54: 3 | R54: 83.7 | S54: 0.24 | T54: PayPal | U54: 190.836 | W54: Sale50 | X54: 45291 | Y54: Cust1070 | Z54: Prod52 | AA54: Store9 | AB54: 3 | AC54: 83.7 | AD54: 0.24 | AE54: Paypal | AF54: 190.836
A55: SALE51 | B55: 45689 | C55: CUST1142 | D55: PROD69 | E55: STORE7 | F55: 3 | G55: 76.57 | H55: 0.26 | I55: Credit Card | J55: 169.9854 | L55: SALE51 | M55: 45689 | N55: CUST1142 | O55: PROD69 | P55: STORE7 | Q55: 3 | R55: 76.57 | S55: 0.26 | T55: Credit Card | U55: 169.9854 | W55: Sale51 | X55: 45689 | Y55: Cust1142 | Z55: Prod69 | AA55: Store7 | AB55: 3 | AC55: 76.57 | AD55: 0.26 | AE55: Credit Card | AF55: 169.9854
A56: SALE52 | B56: 45894 | C56: CUST1148 | D56: PROD89 | E56: STORE6 | F56: 3 | I56: Credit Card | J56: 486.0633 | L56: SALE52 | M56: 45894 | N56: CUST1148 | O56: PROD89 | P56: STORE6 | Q56: 3 | T56: Credit Card | U56: 486.0633 | W56: Sale52 | X56: 45894 | Y56: Cust1148 | Z56: Prod89 | AA56: Store6 | AB56: 3 | AE56: Credit Card | AF56: 486.0633
A57: SALE53 | B57: 45677 | C57: CUST1324 | D57: PROD20 | E57: STORE8 | F57: 1 | G57: 900.35 | H57: 0.13 | I57: COD | J57: 783.3045 | L57: SALE53 | M57: 45677 | N57: CUST1324 | O57: PROD20 | P57: STORE8 | Q57: 1 | R57: 900.35 | S57: 0.13 | T57: COD | U57: 783.3045 | W57: Sale53 | X57: 45677 | Y57: Cust1324 | Z57: Prod20 | AA57: Store8 | AB57: 1 | AC57: 900.35 | AD57: 0.13 | AE57: Cod | AF57: 783.3045
A58: SALE54 | B58: 45706 | C58: CUST1095 | D58: PROD40 | E58: STORE10 | F58: 4 | G58: 428.09 | H58: 0.07 | I58: Credit Card | J58: 1592.4948 | L58: SALE54 | M58: 45706 | N58: CUST1095 | O58: PROD40 | P58: STORE10 | Q58: 4 | R58: 428.09 | S58: 0.07 | T58: Credit Card | U58: 1592.4948 | W58: Sale54 | X58: 45706 | Y58: Cust1095 | Z58: Prod40 | AA58: Store10 | AB58: 4 | AC58: 428.09 | AD58: 0.07 | AE58: Credit Card | AF58: 1592.4948
A59: SALE55 | B59: 45589 | C59: CUST1416 | D59: PROD49 | E59: STORE11 | F59: 2 | G59: 559.71 | H59: 0.3 | I59: COD | J59: 783.594 | L59: SALE55 | M59: 45589 | N59: CUST1416 | O59: PROD49 | P59: STORE11 | Q59: 2 | R59: 559.71 | S59: 0.3 | T59: COD | U59: 783.594 | W59: Sale55 | X59: 45589 | Y59: Cust1416 | Z59: Prod49 | AA59: Store11 | AB59: 2 | AC59: 559.71 | AD59: 0.3 | AE59: Cod | AF59: 783.594
A60: SALE56 | B60: 45282 | C60: CUST1080 | D60: PROD34 | E60: STORE6 | F60: 2 | G60: 833.7 | H60: 0.06 | I60: PayPal | J60: 1567.356 | L60: SALE56 | M60: 45282 | N60: CUST1080 | O60: PROD34 | P60: STORE6 | Q60: 2 | R60: 833.7 | S60: 0.06 | T60: PayPal | U60: 1567.356 | W60: Sale56 | X60: 45282 | Y60: Cust1080 | Z60: Prod34 | AA60: Store6 | AB60: 2 | AC60: 833.7 | AD60: 0.06 | AE60: Paypal | AF60: 1567.356
A61: SALE57 | B61: 45462 | C61: CUST1467 | D61: PROD47 | E61: STORE14 | F61: 2 | G61: 680.16 | H61: 0.28 | I61: Credit Card | J61: 979.4304 | L61: SALE57 | M61: 45462 | N61: CUST1467 | O61: PROD47 | P61: STORE14 | Q61: 2 | R61: 680.16 | S61: 0.28 | T61: Credit Card | U61: 979.4304 | W61: Sale57 | X61: 45462 | Y61: Cust1467 | Z61: Prod47 | AA61: Store14 | AB61: 2 | AC61: 680.16 | AD61: 0.28 | AE61: Credit Card | AF61: 979.4304
A62: SALE58 | B62: 45633 | C62: CUST1404 | D62: PROD15 | E62: STORE7 | F62: 4 | G62: 733.42 | I62: PayPal | J62: 2552.3016 | L62: SALE58 | M62: 45633 | N62: CUST1404 | O62: PROD15 | P62: STORE7 | Q62: 4 | R62: 733.42 | T62: PayPal | U62: 2552.3016 | W62: Sale58 | X62: 45633 | Y62: Cust1404 | Z62: Prod15 | AA62: Store7 | AB62: 4 | AC62: 733.42 | AE62: Paypal | AF62: 2552.3016
A63: SALE59 | B63: 45257 | C63: CUST1367 | D63: PROD89 | E63: STORE11 | F63: 1 | G63: 996.33 | H63: 0.23 | I63: PayPal | J63: 767.1741 | L63: SALE59 | M63: 45257 | N63: CUST1367 | O63: PROD89 | P63: STORE11 | Q63: 1 | R63: 996.33 | S63: 0.23 | T63: PayPal | U63: 767.1741 | W63: Sale59 | X63: 45257 | Y63: Cust1367 | Z63: Prod89 | AA63: Store11 | AB63: 1 | AC63: 996.33 | AD63: 0.23 | AE63: Paypal | AF63: 767.1741
A64: SALE60 | B64: 45854 | C64: CUST1408 | D64: PROD31 | E64: STORE10 | F64: 1 | G64: 198.83 | H64: 0.09 | I64: COD | J64: 180.9353 | L64: SALE60 | M64: 45854 | N64: CUST1408 | O64: PROD31 | P64: STORE10 | Q64: 1 | R64: 198.83 | S64: 0.09 | T64: COD | U64: 180.9353 | W64: Sale60 | X64: 45854 | Y64: Cust1408 | Z64: Prod31 | AA64: Store10 | AB64: 1 | AC64: 198.83 | AD64: 0.09 | AE64: Cod | AF64: 180.9353
A65: SALE61 | B65: 45716 | C65: CUST1239 | D65: PROD19 | E65: STORE7 | F65: 1 | G65: 374.92 | H65: 0.18 | I65: PayPal | J65: 307.4344 | L65: SALE61 | M65: 45716 | N65: CUST1239 | O65: PROD19 | P65: STORE7 | Q65: 1 | R65: 374.92 | S65: 0.18 | T65: PayPal | U65: 307.4344 | W65: Sale61 | X65: 45716 | Y65: Cust1239 | Z65: Prod19 | AA65: Store7 | AB65: 1 | AC65: 374.92 | AD65: 0.18 | AE65: Paypal | AF65: 307.4344
A66: SALE62 | B66: 45515 | C66: CUST1464 | D66: PROD93 | E66: STORE16 | F66: 1 | G66: 468.94 | H66: 0.12 | I66: Credit Card | J66: 412.6672 | L66: SALE62 | M66: 45515 | N66: CUST1464 | O66: PROD93 | P66: STORE16 | Q66: 1 | R66: 468.94 | S66: 0.12 | T66: Credit Card | U66: 412.6672 | W66: Sale62 | X66: 45515 | Y66: Cust1464 | Z66: Prod93 | AA66: Store16 | AB66: 1 | AC66: 468.94 | AD66: 0.12 | AE66: Credit Card | AF66: 412.6672
A67: SALE63 | B67: 45927 | C67: CUST1126 | D67: PROD89 | E67: STORE12 | F67: 2 | G67: 121.37 | H67: 0.05 | I67: Credit Card | J67: 230.603 | L67: SALE63 | M67: 45927 | N67: CUST1126 | O67: PROD89 | P67: STORE12 | Q67: 2 | R67: 121.37 | S67: 0.05 | T67: Credit Card | U67: 230.603 | W67: Sale63 | X67: 45927 | Y67: Cust1126 | Z67: Prod89 | AA67: Store12 | AB67: 2 | AC67: 121.37 | AD67: 0.05 | AE67: Credit Card | AF67: 230.603
A68: SALE64 | B68: 45914 | C68: CUST1255 | D68: PROD53 | E68: STORE10 | F68: 3 | G68: 480.06 | H68: 0.01 | I68: Credit Card | L68: SALE64 | M68: 45914 | N68: CUST1255 | O68: PROD53 | P68: STORE10 | Q68: 3 | R68: 480.06 | S68: 0.01 | T68: Credit Card | W68: Sale64 | X68: 45914 | Y68: Cust1255 | Z68: Prod53 | AA68: Store10 | AB68: 3 | AC68: 480.06 | AD68: 0.01 | AE68: Credit Card
A69: SALE65 | B69: 45290 | C69: CUST1162 | D69: PROD99 | E69: STORE17 | F69: 2 | G69: 856.57 | H69: 0.24 | I69: Credit Card | J69: 1301.9864 | L69: SALE65 | M69: 45290 | N69: CUST1162 | O69: PROD99 | P69: STORE17 | Q69: 2 | R69: 856.57 | S69: 0.24 | T69: Credit Card | U69: 1301.9864 | W69: Sale65 | X69: 45290 | Y69: Cust1162 | Z69: Prod99 | AA69: Store17 | AB69: 2 | AC69: 856.57 | AD69: 0.24 | AE69: Credit Card | AF69: 1301.9864
A70: SALE66 | B70: 45213 | C70: CUST1269 | D70: PROD77 | E70: STORE2 | F70: 4 | G70: 814.25 | H70: 0.18 | I70: Credit Card | J70: 2670.74 | L70: SALE66 | M70: 45213 | N70: CUST1269 | O70: PROD77 | P70: STORE2 | Q70: 4 | R70: 814.25 | S70: 0.18 | T70: Credit Card | U70: 2670.74 | W70: Sale66 | X70: 45213 | Y70: Cust1269 | Z70: Prod77 | AA70: Store2 | AB70: 4 | AC70: 814.25 | AD70: 0.18 | AE70: Credit Card | AF70: 2670.74
A71: SALE67 | B71: 45255 | C71: CUST1483 | D71: PROD12 | E71: STORE2 | F71: 1 | G71: 989.17 | H71: 0.2 | I71: PayPal | J71: 791.336 | L71: SALE67 | M71: 45255 | N71: CUST1483 | O71: PROD12 | P71: STORE2 | Q71: 1 | R71: 989.17 | S71: 0.2 | T71: PayPal | U71: 791.336 | W71: Sale67 | X71: 45255 | Y71: Cust1483 | Z71: Prod12 | AA71: Store2 | AB71: 1 | AC71: 989.17 | AD71: 0.2 | AE71: Paypal | AF71: 791.336
A72: SALE68 | B72: 45270 | C72: CUST1372 | D72: PROD72 | E72: STORE10 | F72: 4 | G72: 62.48 | H72: 0.18 | I72: Credit Card | J72: 204.9344 | L72: SALE68 | M72: 45270 | N72: CUST1372 | O72: PROD72 | P72: STORE10 | Q72: 4 | R72: 62.48 | S72: 0.18 | T72: Credit Card | U72: 204.9344 | W72: Sale68 | X72: 45270 | Y72: Cust1372 | Z72: Prod72 | AA72: Store10 | AB72: 4 | AC72: 62.48 | AD72: 0.18 | AE72: Credit Card | AF72: 204.9344
A73: SALE69 | B73: 45897 | C73: CUST1423 | D73: PROD13 | E73: STORE16 | F73: 4 | G73: 561.24 | H73: 0.24 | I73: Credit Card | J73: 1706.1696 | L73: SALE69 | M73: 45897 | N73: CUST1423 | O73: PROD13 | P73: STORE16 | Q73: 4 | R73: 561.24 | S73: 0.24 | T73: Credit Card | U73: 1706.1696 | W73: Sale69 | X73: 45897 | Y73: Cust1423 | Z73: Prod13 | AA73: Store16 | AB73: 4 | AC73: 561.24 | AD73: 0.24 | AE73: Credit Card | AF73: 1706.1696
A74: SALE70 | B74: 45849 | C74: CUST1058 | D74: PROD60 | E74: STORE5 | F74: 3 | G74: 92.24 | H74: 0.28 | I74: COD | L74: SALE70 | M74: 45849 | N74: CUST1058 | O74: PROD60 | P74: STORE5 | Q74: 3 | R74: 92.24 | S74: 0.28 | T74: COD | W74: Sale70 | X74: 45849 | Y74: Cust1058 | Z74: Prod60 | AA74: Store5 | AB74: 3 | AC74: 92.24 | AD74: 0.28 | AE74: Cod
A75: SALE71 | B75: 45889 | C75: CUST1168 | D75: PROD72 | E75: STORE1 | F75: 2 | G75: 668.3 | H75: 0.07 | I75: Credit Card | J75: 1243.038 | L75: SALE71 | M75: 45889 | N75: CUST1168 | O75: PROD72 | P75: STORE1 | Q75: 2 | R75: 668.3 | S75: 0.07 | T75: Credit Card | U75: 1243.038 | W75: Sale71 | X75: 45889 | Y75: Cust1168 | Z75: Prod72 | AA75: Store1 | AB75: 2 | AC75: 668.3 | AD75: 0.07 | AE75: Credit Card | AF75: 1243.038
A76: SALE72 | B76: 45533 | C76: CUST1409 | D76: PROD38 | E76: STORE5 | F76: 1 | G76: 553.82 | H76: 0.09 | I76: Credit Card | J76: 503.9762 | L76: SALE72 | M76: 45533 | N76: CUST1409 | O76: PROD38 | P76: STORE5 | Q76: 1 | R76: 553.82 | S76: 0.09 | T76: Credit Card | U76: 503.9762 | W76: Sale72 | X76: 45533 | Y76: Cust1409 | Z76: Prod38 | AA76: Store5 | AB76: 1 | AC76: 553.82 | AD76: 0.09 | AE76: Credit Card | AF76: 503.9762
A77: SALE73 | B77: 45626 | C77: CUST1037 | D77: PROD45 | E77: STORE11 | F77: 2 | G77: 556.43 | H77: 0.13 | I77: Credit Card | J77: 968.1882 | L77: SALE73 | M77: 45626 | N77: CUST1037 | O77: PROD45 | P77: STORE11 | Q77: 2 | R77: 556.43 | S77: 0.13 | T77: Credit Card | U77: 968.1882 | W77: Sale73 | X77: 45626 | Y77: Cust1037 | Z77: Prod45 | AA77: Store11 | AB77: 2 | AC77: 556.43 | AD77: 0.13 | AE77: Credit Card | AF77: 968.1882
A78: SALE74 | B78: 45942 | C78: CUST1273 | D78: PROD20 | E78: STORE8 | F78: 1 | G78: 184.98 | H78: 0.1 | I78: COD | J78: 166.482 | L78: SALE74 | M78: 45942 | N78: CUST1273 | O78: PROD20 | P78: STORE8 | Q78: 1 | R78: 184.98 | S78: 0.1 | T78: COD | U78: 166.482 | W78: Sale74 | X78: 45942 | Y78: Cust1273 | Z78: Prod20 | AA78: Store8 | AB78: 1 | AC78: 184.98 | AD78: 0.1 | AE78: Cod | AF78: 166.482
A79: SALE75 | B79: 45500 | C79: CUST1035 | D79: PROD97 | E79: STORE12 | F79: 4 | G79: 700.18 | H79: 0.23 | I79: Credit Card | J79: 2156.5544 | L79: SALE75 | M79: 45500 | N79: CUST1035 | O79: PROD97 | P79: STORE12 | Q79: 4 | R79: 700.18 | S79: 0.23 | T79: Credit Card | U79: 2156.5544 | W79: Sale75 | X79: 45500 | Y79: Cust1035 | Z79: Prod97 | AA79: Store12 | AB79: 4 | AC79: 700.18 | AD79: 0.23 | AE79: Credit Card | AF79: 2156.5544
A80: SALE76 | B80: 45285 | C80: CUST1019 | D80: PROD76 | E80: STORE10 | F80: 2 | G80: 686.31 | H80: 0.25 | I80: Credit Card | J80: 1029.465 | L80: SALE76 | M80: 45285 | N80: CUST1019 | O80: PROD76 | P80: STORE10 | Q80: 2 | R80: 686.31 | S80: 0.25 | T80: Credit Card | U80: 1029.465 | W80: Sale76 | X80: 45285 | Y80: Cust1019 | Z80: Prod76 | AA80: Store10 | AB80: 2 | AC80: 686.31 | AD80: 0.25 | AE80: Credit Card | AF80: 1029.465
A81: SALE77 | B81: 45800 | C81: CUST1007 | D81: PROD67 | E81: STORE15 | F81: 1 | G81: 687.82 | H81: 0.27 | I81: COD | J81: 502.1086 | L81: SALE77 | M81: 45800 | N81: CUST1007 | O81: PROD67 | P81: STORE15 | Q81: 1 | R81: 687.82 | S81: 0.27 | T81: COD | U81: 502.1086 | W81: Sale77 | X81: 45800 | Y81: Cust1007 | Z81: Prod67 | AA81: Store15 | AB81: 1 | AC81: 687.82 | AD81: 0.27 | AE81: Cod | AF81: 502.1086
A82: SALE78 | B82: 45609 | C82: CUST1221 | D82: PROD83 | E82: STORE8 | F82: 2 | G82: 900.55 | H82: 0.16 | I82: Credit Card | J82: 1512.924 | L82: SALE78 | M82: 45609 | N82: CUST1221 | O82: PROD83 | P82: STORE8 | Q82: 2 | R82: 900.55 | S82: 0.16 | T82: Credit Card | U82: 1512.924 | W82: Sale78 | X82: 45609 | Y82: Cust1221 | Z82: Prod83 | AA82: Store8 | AB82: 2 | AC82: 900.55 | AD82: 0.16 | AE82: Credit Card | AF82: 1512.924
A83: SALE79 | B83: 45268 | C83: CUST1115 | D83: PROD21 | E83: STORE2 | F83: 1 | G83: 341.17 | H83: 0.15 | I83: Credit Card | J83: 289.9945 | L83: SALE79 | M83: 45268 | N83: CUST1115 | O83: PROD21 | P83: STORE2 | Q83: 1 | R83: 341.17 | S83: 0.15 | T83: Credit Card | U83: 289.9945 | W83: Sale79 | X83: 45268 | Y83: Cust1115 | Z83: Prod21 | AA83: Store2 | AB83: 1 | AC83: 341.17 | AD83: 0.15 | AE83: Credit Card | AF83: 289.9945
A84: SALE80 | B84: 45885 | C84: CUST1176 | D84: PROD52 | E84: STORE8 | F84: 1 | G84: 442.27 | H84: 0.06 | I84: COD | J84: 415.7338 | L84: SALE80 | M84: 45885 | N84: CUST1176 | O84: PROD52 | P84: STORE8 | Q84: 1 | R84: 442.27 | S84: 0.06 | T84: COD | U84: 415.7338 | W84: Sale80 | X84: 45885 | Y84: Cust1176 | Z84: Prod52 | AA84: Store8 | AB84: 1 | AC84: 442.27 | AD84: 0.06 | AE84: Cod | AF84: 415.7338
A85: SALE81 | B85: 45616 | C85: CUST1253 | D85: PROD71 | E85: STORE9 | F85: 1 | G85: 363.73 | H85: 0.25 | I85: PayPal | J85: 272.7975 | L85: SALE81 | M85: 45616 | N85: CUST1253 | O85: PROD71 | P85: STORE9 | Q85: 1 | R85: 363.73 | S85: 0.25 | T85: PayPal | U85: 272.7975 | W85: Sale81 | X85: 45616 | Y85: Cust1253 | Z85: Prod71 | AA85: Store9 | AB85: 1 | AC85: 363.73 | AD85: 0.25 | AE85: Paypal | AF85: 272.7975
A86: SALE82 | B86: 45518 | C86: CUST1378 | D86: PROD91 | E86: STORE17 | F86: 2 | G86: 601.33 | H86: 0.16 | I86: PayPal | J86: 1010.2344 | L86: SALE82 | M86: 45518 | N86: CUST1378 | O86: PROD91 | P86: STORE17 | Q86: 2 | R86: 601.33 | S86: 0.16 | T86: PayPal | U86: 1010.2344 | W86: Sale82 | X86: 45518 | Y86: Cust1378 | Z86: Prod91 | AA86: Store17 | AB86: 2 | AC86: 601.33 | AD86: 0.16 | AE86: Paypal | AF86: 1010.2344
A87: SALE83 | B87: 45427 | C87: CUST1403 | D87: PROD17 | E87: STORE18 | F87: 4 | G87: 34.39 | H87: 0.03 | I87: PayPal | J87: 133.4332 | L87: SALE83 | M87: 45427 | N87: CUST1403 | O87: PROD17 | P87: STORE18 | Q87: 4 | R87: 34.39 | S87: 0.03 | T87: PayPal | U87: 133.4332 | W87: Sale83 | X87: 45427 | Y87: Cust1403 | Z87: Prod17 | AA87: Store18 | AB87: 4 | AC87: 34.39 | AD87: 0.03 | AE87: Paypal | AF87: 133.4332
A88: SALE84 | B88: 45268 | C88: CUST1423 | D88: PROD46 | E88: STORE17 | F88: 1 | G88: 773.57 | H88: 0.05 | I88: COD | L88: SALE84 | M88: 45268 | N88: CUST1423 | O88: PROD46 | P88: STORE17 | Q88: 1 | R88: 773.57 | S88: 0.05 | T88: COD | W88: Sale84 | X88: 45268 | Y88: Cust1423 | Z88: Prod46 | AA88: Store17 | AB88: 1 | AC88: 773.57 | AD88: 0.05 | AE88: Cod
A89: SALE85 | B89: 45282 | C89: CUST1054 | D89: PROD88 | E89: STORE7 | F89: 4 | G89: 127.1 | H89: 0.24 | I89: COD | J89: 386.384 | L89: SALE85 | M89: 45282 | N89: CUST1054 | O89: PROD88 | P89: STORE7 | Q89: 4 | R89: 127.1 | S89: 0.24 | T89: COD | U89: 386.384 | W89: Sale85 | X89: 45282 | Y89: Cust1054 | Z89: Prod88 | AA89: Store7 | AB89: 4 | AC89: 127.1 | AD89: 0.24 | AE89: Cod | AF89: 386.384
A90: SALE86 | B90: 45545 | C90: CUST1303 | D90: PROD20 | E90: STORE3 | F90: 3 | G90: 899.58 | H90: 0.28 | I90: PayPal | J90: 1943.0928 | L90: SALE86 | M90: 45545 | N90: CUST1303 | O90: PROD20 | P90: STORE3 | Q90: 3 | R90: 899.58 | S90: 0.28 | T90: PayPal | U90: 1943.0928 | W90: Sale86 | X90: 45545 | Y90: Cust1303 | Z90: Prod20 | AA90: Store3 | AB90: 3 | AC90: 899.58 | AD90: 0.28 | AE90: Paypal | AF90: 1943.0928
A91: SALE87 | B91: 45755 | C91: CUST1327 | D91: PROD1 | E91: STORE10 | F91: 3 | G91: 964.39 | H91: 0.04 | I91: Credit Card | J91: 2777.4432 | L91: SALE87 | M91: 45755 | N91: CUST1327 | O91: PROD1 | P91: STORE10 | Q91: 3 | R91: 964.39 | S91: 0.04 | T91: Credit Card | U91: 2777.4432 | W91: Sale87 | X91: 45755 | Y91: Cust1327 | Z91: Prod1 | AA91: Store10 | AB91: 3 | AC91: 964.39 | AD91: 0.04 | AE91: Credit Card | AF91: 2777.4432
A92: SALE88 | B92: 45588 | C92: CUST1183 | D92: PROD38 | E92: STORE0 | F92: 2 | G92: 217.83 | H92: 0.14 | I92: PayPal | J92: 374.6676 | L92: SALE88 | M92: 45588 | N92: CUST1183 | O92: PROD38 | P92: STORE0 | Q92: 2 | R92: 217.83 | S92: 0.14 | T92: PayPal | U92: 374.6676 | W92: Sale88 | X92: 45588 | Y92: Cust1183 | Z92: Prod38 | AA92: Store0 | AB92: 2 | AC92: 217.83 | AD92: 0.14 | AE92: Paypal | AF92: 374.6676
A93: SALE89 | B93: 45848 | C93: CUST1143 | D93: PROD17 | E93: STORE1 | F93: 4 | G93: 187.71 | H93: 0.06 | I93: COD | J93: 705.7896 | L93: SALE89 | M93: 45848 | N93: CUST1143 | O93: PROD17 | P93: STORE1 | Q93: 4 | R93: 187.71 | S93: 0.06 | T93: COD | U93: 705.7896 | W93: Sale89 | X93: 45848 | Y93: Cust1143 | Z93: Prod17 | AA93: Store1 | AB93: 4 | AC93: 187.71 | AD93: 0.06 | AE93: Cod | AF93: 705.7896
A94: SALE90 | B94: 45577 | C94: CUST1010 | D94: PROD33 | E94: STORE18 | F94: 2 | G94: 350.12 | H94: 0.12 | I94: COD | J94: 616.2112 | L94: SALE90 | M94: 45577 | N94: CUST1010 | O94: PROD33 | P94: STORE18 | Q94: 2 | R94: 350.12 | S94: 0.12 | T94: COD | U94: 616.2112 | W94: Sale90 | X94: 45577 | Y94: Cust1010 | Z94: Prod33 | AA94: Store18 | AB94: 2 | AC94: 350.12 | AD94: 0.12 | AE94: Cod | AF94: 616.2112
A95: SALE91 | B95: 45312 | C95: CUST1406 | D95: PROD16 | E95: STORE1 | F95: 4 | G95: 102.19 | H95: 0.17 | I95: PayPal | J95: 339.2708 | L95: SALE91 | M95: 45312 | N95: CUST1406 | O95: PROD16 | P95: STORE1 | Q95: 4 | R95: 102.19 | S95: 0.17 | T95: PayPal | U95: 339.2708 | W95: Sale91 | X95: 45312 | Y95: Cust1406 | Z95: Prod16 | AA95: Store1 | AB95: 4 | AC95: 102.19 | AD95: 0.17 | AE95: Paypal | AF95: 339.2708
A96: SALE92 | B96: 45350 | C96: CUST1007 | D96: PROD86 | E96: STORE4 | F96: 1 | G96: 696.53 | H96: 0.17 | I96: Credit Card | J96: 578.1199 | L96: SALE92 | M96: 45350 | N96: CUST1007 | O96: PROD86 | P96: STORE4 | Q96: 1 | R96: 696.53 | S96: 0.17 | T96: Credit Card | U96: 578.1199 | W96: Sale92 | X96: 45350 | Y96: Cust1007 | Z96: Prod86 | AA96: Store4 | AB96: 1 | AC96: 696.53 | AD96: 0.17 | AE96: Credit Card | AF96: 578.1199
A97: SALE93 | B97: 45657 | C97: CUST1065 | D97: PROD19 | E97: STORE4 | F97: 2 | G97: 327.52 | H97: 0.15 | I97: PayPal | J97: 556.784 | L97: SALE93 | M97: 45657 | N97: CUST1065 | O97: PROD19 | P97: STORE4 | Q97: 2 | R97: 327.52 | S97: 0.15 | T97: PayPal | U97: 556.784 | W97: Sale93 | X97: 45657 | Y97: Cust1065 | Z97: Prod19 | AA97: Store4 | AB97: 2 | AC97: 327.52 | AD97: 0.15 | AE97: Paypal | AF97: 556.784
A98: SALE94 | B98: 45530 | C98: CUST1298 | D98: PROD97 | E98: STORE19 | F98: 2 | G98: 569.36 | H98: 0.01 | I98: PayPal | L98: SALE94 | M98: 45530 | N98: CUST1298 | O98: PROD97 | P98: STORE19 | Q98: 2 | R98: 569.36 | S98: 0.01 | T98: PayPal | W98: Sale94 | X98: 45530 | Y98: Cust1298 | Z98: Prod97 | AA98: Store19 | AB98: 2 | AC98: 569.36 | AD98: 0.01 | AE98: Paypal
A99: SALE95 | B99: 45556 | C99: CUST1321 | D99: PROD99 | E99: STORE6 | F99: 2 | G99: 68.29 | H99: 0.14 | I99: COD | J99: 117.4588 | L99: SALE95 | M99: 45556 | N99: CUST1321 | O99: PROD99 | P99: STORE6 | Q99: 2 | R99: 68.29 | S99: 0.14 | T99: COD | U99: 117.4588 | W99: Sale95 | X99: 45556 | Y99: Cust1321 | Z99: Prod99 | AA99: Store6 | AB99: 2 | AC99: 68.29 | AD99: 0.14 | AE99: Cod | AF99: 117.4588
A100: SALE96 | B100: 45523 | C100: CUST1244 | D100: PROD50 | E100: STORE10 | F100: 1 | G100: 842.9 | H100: 0.06 | I100: COD | J100: 792.326 | L100: SALE96 | M100: 45523 | N100: CUST1244 | O100: PROD50 | P100: STORE10 | Q100: 1 | R100: 842.9 | S100: 0.06 | T100: COD | U100: 792.326 | W100: Sale96 | X100: 45523 | Y100: Cust1244 | Z100: Prod50 | AA100: Store10 | AB100: 1 | AC100: 842.9 | AD100: 0.06 | AE100: Cod | AF100: 792.326
A101: SALE97 | B101: 45587 | C101: CUST1287 | D101: PROD3 | E101: STORE3 | F101: 3 | G101: 751.94 | H101: 0.26 | I101: PayPal | J101: 1669.3068 | L101: SALE97 | M101: 45587 | N101: CUST1287 | O101: PROD3 | P101: STORE3 | Q101: 3 | R101: 751.94 | S101: 0.26 | T101: PayPal | U101: 1669.3068 | W101: Sale97 | X101: 45587 | Y101: Cust1287 | Z101: Prod3 | AA101: Store3 | AB101: 3 | AC101: 751.94 | AD101: 0.26 | AE101: Paypal | AF101: 1669.3068
...

Sheet f Excel formulas for calculatio
A1: Sales_ID | B1: Order_Date | C1: Customer_ID | D1: Product_ID | E1: Store_ID | F1: Quantity | G1: Unit_Price | H1: Discount | I1: Payment_Type | J1: Total_Amount
A2: SALE0 | B2: 45480 | C2: CUST1409 | D2: PROD97 | E2: STORE3 | F2: 1 | G2: 218.04 | H2: 0.09 | I2: Credit Card | J2: 198.4164
A3: SALE1 | B3: 45285 | C3: CUST1467 | D3: PROD74 | E3: STORE17 | F3: 3 | G3: 104.47 | H3: 0.27 | I3: PayPal | J3: 228.7893
A4: SALE2 | B4: 45446 | C4: CUST1056 | D4: PROD49 | E4: STORE8 | F4: 4 | G4: 914.05 | H4: 0.25 | I4: Credit Card | J4: 2742.15
A5: SALE3 | B5: 45259 | C5: CUST1346 | D5: PROD76 | E5: STORE8 | F5: 1 | G5: 921.51 | H5: 0.16 | I5: COD | J5: 774.0684
A6: SALE4 | B6: 45297 | C6: CUST1493 | D6: PROD59 | E6: STORE5 | F6: 3 | G6: 745.3 | H6: 0.18 | I6: Credit Card | J6: 1833.438
A7: SALE5 | B7: 45499 | C7: CUST1116 | D7: PROD15 | E7: STORE7 | F7: 3 | G7: 147.01 | H7: 0.19 | I7: COD | J7: 357.2343
A8: SALE6 | B8: 45850 | C8: CUST1016 | D8: PROD56 | E8: STORE4 | F8: 2 | G8: 785.31 | H8: 0.15 | I8: PayPal | J8: 1335.027
A9: SALE7 | B9: 45248 | C9: CUST1152 | D9: PROD70 | E9: STORE8 | F9: 4 | G9: 342.39 | H9: 0.23 | I9: PayPal | J9: 1054.5612
A10: SALE8 | B10: 45781 | C10: CUST1187 | D10: PROD99 | E10: STORE5 | G10: 448.25 | H10: 0.07 | I10: PayPal | J10: 1250.6175
A11: SALE9 | B11: 45869 | C11: CUST1464 | D11: PROD33 | E11: STORE0 | F11: 2 | G11: 873.17 | H11: 0.23 | I11: PayPal | J11: 1344.6818
A12: SALE10 | B12: 45335 | C12: CUST1065 | D12: PROD24 | E12: STORE14 | F12: 1 | G12: 278.63 | H12: 0.07 | I12: Credit Card | J12: 259.1259
A13: SALE11 | B13: 45801 | C13: CUST1320 | D13: PROD39 | E13: STORE1 | F13: 4 | G13: 286.92 | H13: 0.17 | I13: Credit Card | J13: 952.5744
A14: SALE12 | B14: 45528 | C14: CUST1237 | D14: PROD88 | E14: STORE4 | F14: 4 | G14: 644.58 | H14: 0.01 | I14: Credit Card | J14: 2552.5368
A15: SALE13 | B15: 45875 | C15: CUST1443 | D15: PROD34 | E15: STORE16 | F15: 2 | G15: 316.9 | H15: 0.3 | I15: PayPal | J15: 443.66
A16: SALE14 | B16: 45829 | C16: CUST1348 | D16: PROD24 | E16: STORE15 | F16: 4 | G16: 403.47 | H16: 0.29 | I16: PayPal | J16: 1145.8548
A17: SALE15 | B17: 45636 | C17: CUST1435 | D17: PROD36 | E17: STORE9 | G17: 871.34 | H17: 0.04 | I17: COD | J17: 2509.4592
A18: SALE16 | B18: 45913 | C18: CUST1276 | D18: PROD65 | E18: STORE19 | F18: 2 | G18: 451.98 | H18: 0.25 | I18: Credit Card | J18: 677.97
A19: SALE17 | B19: 45637 | C19: CUST1079 | D19: PROD27 | E19: STORE4 | F19: 2 | G19: 502.69 | H19: 0.23 | I19: Credit Card | J19: 774.1426
A20: SALE18 | B20: 45517 | C20: CUST1094 | D20: PROD39 | E20: STORE4 | F20: 2 | G20: 559.23 | H20: 0.25 | I20: COD | J20: 838.845
A21: SALE19 | B21: 45369 | C21: CUST1239 | D21: PROD60 | E21: STORE13 | F21: 4 | H21: 0.04 | I21: COD | J21: 1782.4512
A22: SALE20 | B22: 45843 | C22: CUST1144 | D22: PROD72 | E22: STORE17 | F22: 3 | G22: 986.04 | H22: 0.27 | I22: COD | J22: 2159.4276
A23: SALE21 | B23: 45447 | C23: CUST1396 | D23: PROD43 | E23: STORE18 | F23: 1 | G23: 589.56 | H23: 0.22 | I23: Credit Card | J23: 459.8568
A24: SALE22 | B24: 45394 | C24: CUST1476 | D24: PROD69 | E24: STORE10 | F24: 3 | G24: 979.42 | H24: 0.03 | I24: PayPal | J24: 2850.1122
A25: SALE23 | B25: 45466 | C25: CUST1368 | D25: PROD12 | E25: STORE8 | F25: 1 | G25: 719.28 | H25: 0.08 | I25: Credit Card | J25: 661.7376
A26: SALE24 | B26: 45908 | C26: CUST1186 | D26: PROD67 | E26: STORE6 | F26: 3 | G26: 77.6 | H26: 0.07 | I26: Credit Card | J26: 216.504
A27: SALE25 | B27: 45552 | C27: CUST1381 | D27: PROD5 | E27: STORE3 | F27: 4 | G27: 852.71 | H27: 0.14 | I27: PayPal | J27: 2933.3224
A28: SALE26 | B28: 45294 | C28: CUST1213 | D28: PROD98 | E28: STORE8 | F28: 4 | G28: 156.16 | I28: Credit Card | J28: 599.6544
A29: SALE27 | B29: 45710 | C29: CUST1200 | D29: PROD77 | E29: STORE8 | F29: 3 | G29: 815.49 | H29: 0.17 | I29: Credit Card | J29: 2030.5701
A30: SALE28 | B30: 45923 | C30: CUST1148 | D30: PROD13 | E30: STORE2 | F30: 2 | G30: 74.21 | H30: 0.11 | I30: PayPal | J30: 132.0938
A31: SALE29 | B31: 45302 | C31: CUST1348 | D31: PROD99 | E31: STORE3 | G31: 451.67 | H31: 0.15 | I31: Credit Card | J31: 1535.678
A32: SALE30 | B32: 45217 | C32: CUST1028 | D32: PROD5 | E32: STORE19 | F32: 1 | G32: 429.38 | H32: 0.13 | I32: PayPal | J32: 373.5606
A33: SALE31 | B33: 45593 | C33: CUST1412 | D33: PROD53 | E33: STORE12 | F33: 2 | G33: 148.96 | H33: 0.03 | I33: COD | J33: 288.9824
A34: SALE32 | B34: 45597 | C34: CUST1398 | D34: PROD75 | E34: STORE8 | F34: 4 | G34: 313.83 | H34: 0.08 | I34: Credit Card | J34: 1154.8944
A35: SALE33 | B35: 45620 | C35: CUST1453 | D35: PROD12 | E35: STORE6 | F35: 2 | G35: 717.31 | H35: 0.15 | I35: Credit Card | J35: 1219.427
A36: SALE34 | B36: 45215 | C36: CUST1344 | D36: PROD79 | E36: STORE1 | G36: 873.22 | H36: 0.18 | I36: Credit Card | J36: 2148.1212
A37: SALE35 | B37: 45878 | C37: CUST1218 | D37: PROD16 | E37: STORE3 | F37: 4 | G37: 109.36 | H37: 0.19 | I37: COD | J37: 354.3264
A38: SALE36 | B38: 45635 | C38: CUST1086 | D38: PROD5 | E38: STORE7 | F38: 3 | G38: 559.52 | H38: 0.16 | I38: PayPal | J38: 1409.9904
A39: SALE37 | B39: 45329 | C39: CUST1492 | D39: PROD10 | E39: STORE17 | F39: 3 | G39: 121.76 | H39: 0.27 | I39: PayPal | J39: 266.6544
A40: SALE38 | B40: 45378 | C40: CUST1189 | D40: PROD33 | E40: STORE13 | F40: 4 | G40: 735.32 | H40: 0.06 | I40: COD | J40: 2764.8032
A41: SALE39 | B41: 45264 | C41: CUST1431 | D41: PROD94 | E41: STORE3 | F41: 2 | G41: 600.73 | H41: 0.08 | I41: Credit Card | J41: 1105.3432
A42: SALE40 | B42: 45486 | C42: CUST1072 | D42: PROD26 | E42: STORE19 | F42: 2 | G42: 873.86 | H42: 0.07 | I42: COD | J42: 1625.3796
A43: SALE41 | B43: 45241 | C43: CUST1302 | D43: PROD23 | E43: STORE8 | F43: 3 | G43: 342.47 | H43: 0.08 | I43: PayPal | J43: 945.2172
A44: SALE42 | B44: 45649 | C44: CUST1335 | D44: PROD29 | E44: STORE9 | F44: 2 | G44: 915.15 | H44: 0.16 | I44: PayPal | J44: 1537.452
A45: SALE43 | B45: 45677 | C45: CUST1084 | D45: PROD33 | E45: STORE17 | G45: 863.11 | H45: 0.28 | I45: PayPal | J45: 1864.3176
A46: SALE44 | B46: 45538 | C46: CUST1203 | D46: PROD43 | E46: STORE12 | F46: 2 | G46: 209.32 | H46: 0.23 | I46: COD | J46: 322.3528
A47: SALE45 | B47: 45606 | C47: CUST1470 | D47: PROD59 | E47: STORE8 | F47: 4 | G47: 288.6 | H47: 0.09 | I47: PayPal | J47: 1050.504
A48: SALE46 | B48: 45570 | C48: CUST1070 | D48: PROD78 | E48: STORE16 | F48: 1 | G48: 418.69 | H48: 0.06 | I48: PayPal | J48: 393.5686
A49: SALE47 | B49: 45466 | C49: CUST1008 | D49: PROD30 | E49: STORE11 | F49: 1 | G49: 135.78 | H49: 0.14 | I49: PayPal | J49: 116.7708
A50: SALE48 | B50: 45218 | C50: CUST1203 | D50: PROD44 | E50: STORE17 | F50: 1 | G50: 517.13 | H50: 0.28 | I50: Credit Card | J50: 372.3336
A51: SALE49 | B51: 45607 | C51: CUST1420 | D51: PROD21 | E51: STORE16 | F51: 2 | G51: 384.66 | H51: 0.08 | I51: COD | J51: 707.7744
A52: SALE50 | B52: 45291 | C52: CUST1070 | D52: PROD52 | E52: STORE9 | F52: 3 | G52: 83.7 | H52: 0.24 | I52: PayPal | J52: 190.836
A53: SALE51 | B53: 45689 | C53: CUST1142 | D53: PROD69 | E53: STORE7 | F53: 3 | G53: 76.57 | H53: 0.26 | I53: Credit Card | J53: 169.9854
A54: SALE52 | B54: 45894 | C54: CUST1148 | D54: PROD89 | E54: STORE6 | F54: 3 | I54: Credit Card | J54: 486.0633
A55: SALE53 | B55: 45677 | C55: CUST1324 | D55: PROD20 | E55: STORE8 | F55: 1 | G55: 900.35 | H55: 0.13 | I55: COD | J55: 783.3045
A56: SALE54 | B56: 45706 | C56: CUST1095 | D56: PROD40 | E56: STORE10 | F56: 4 | G56: 428.09 | H56: 0.07 | I56: Credit Card | J56: 1592.4948
A57: SALE55 | B57: 45589 | C57: CUST1416 | D57: PROD49 | E57: STORE11 | F57: 2 | G57: 559.71 | H57: 0.3 | I57: COD | J57: 783.594
A58: SALE56 | B58: 45282 | C58: CUST1080 | D58: PROD34 | E58: STORE6 | F58: 2 | G58: 833.7 | H58: 0.06 | I58: PayPal | J58: 1567.356
A59: SALE57 | B59: 45462 | C59: CUST1467 | D59: PROD47 | E59: STORE14 | F59: 2 | G59: 680.16 | H59: 0.28 | I59: Credit Card | J59: 979.4304
A60: SALE58 | B60: 45633 | C60: CUST1404 | D60: PROD15 | E60: STORE7 | F60: 4 | G60: 733.42 | I60: PayPal | J60: 2552.3016
A61: SALE59 | B61: 45257 | C61: CUST1367 | D61: PROD89 | E61: STORE11 | F61: 1 | G61: 996.33 | H61: 0.23 | I61: PayPal | J61: 767.1741
A62: SALE60 | B62: 45854 | C62: CUST1408 | D62: PROD31 | E62: STORE10 | F62: 1 | G62: 198.83 | H62: 0.09 | I62: COD | J62: 180.9353
A63: SALE61 | B63: 45716 | C63: CUST1239 | D63: PROD19 | E63: STORE7 | F63: 1 | G63: 374.92 | H63: 0.18 | I63: PayPal | J63: 307.4344
A64: SALE62 | B64: 45515 | C64: CUST1464 | D64: PROD93 | E64: STORE16 | F64: 1 | G64: 468.94 | H64: 0.12 | I64: Credit Card | J64: 412.6672
A65: SALE63 | B65: 45927 | C65: CUST1126 | D65: PROD89 | E65: STORE12 | F65: 2 | G65: 121.37 | H65: 0.05 | I65: Credit Card | J65: 230.603
A66: SALE64 | B66: 45914 | C66: CUST1255 | D66: PROD53 | E66: STORE10 | F66: 3 | G66: 480.06 | H66: 0.01 | I66: Credit Card
A67: SALE65 | B67: 45290 | C67: CUST1162 | D67: PROD99 | E67: STORE17 | F67: 2 | G67: 856.57 | H67: 0.24 | I67: Credit Card | J67: 1301.9864
A68: SALE66 | B68: 45213 | C68: CUST1269 | D68: PROD77 | E68: STORE2 | F68: 4 | G68: 814.25 | H68: 0.18 | I68: Credit Card | J68: 2670.74
A69: SALE67 | B69: 45255 | C69: CUST1483 | D69: PROD12 | E69: STORE2 | F69: 1 | G69: 989.17 | H69: 0.2 | I69: PayPal | J69: 791.336
A70: SALE68 | B70: 45270 | C70: CUST1372 | D70: PROD72 | E70: STORE10 | F70: 4 | G70: 62.48 | H70: 0.18 | I70: Credit Card | J70: 204.9344
A71: SALE69 | B71: 45897 | C71: CUST1423 | D71: PROD13 | E71: STORE16 | F71: 4 | G71: 561.24 | H71: 0.24 | I71: Credit Card | J71: 1706.1696
A72: SALE70 | B72: 45849 | C72: CUST1058 | D72: PROD60 | E72: STORE5 | F72: 3 | G72: 92.24 | H72: 0.28 | I72: COD
A73: SALE71 | B73: 45889 | C73: CUST1168 | D73: PROD72 | E73: STORE1 | F73: 2 | G73: 668.3 | H73: 0.07 | I73: Credit Card | J73: 1243.038
A74: SALE72 | B74: 45533 | C74: CUST1409 | D74: PROD38 | E74: STORE5 | F74: 1 | G74: 553.82 | H74: 0.09 | I74: Credit Card | J74: 503.9762
A75: SALE73 | B75: 45626 | C75: CUST1037 | D75: PROD45 | E75: STORE11 | F75: 2 | G75: 556.43 | H75: 0.13 | I75: Credit Card | J75: 968.1882
A76: SALE74 | B76: 45942 | C76: CUST1273 | D76: PROD20 | E76: STORE8 | F76: 1 | G76: 184.98 | H76: 0.1 | I76: COD | J76: 166.482
A77: SALE75 | B77: 45500 | C77: CUST1035 | D77: PROD97 | E77: STORE12 | F77: 4 | G77: 700.18 | H77: 0.23 | I77: Credit Card | J77: 2156.5544
A78: SALE76 | B78: 45285 | C78: CUST1019 | D78: PROD76 | E78: STORE10 | F78: 2 | G78: 686.31 | H78: 0.25 | I78: Credit Card | J78: 1029.465
A79: SALE77 | B79: 45800 | C79: CUST1007 | D79: PROD67 | E79: STORE15 | F79: 1 | G79: 687.82 | H79: 0.27 | I79: COD | J79: 502.1086
A80: SALE78 | B80: 45609 | C80: CUST1221 | D80: PROD83 | E80: STORE8 | F80: 2 | G80: 900.55 | H80: 0.16 | I80: Credit Card | J80: 1512.924
A81: SALE79 | B81: 45268 | C81: CUST1115 | D81: PROD21 | E81: STORE2 | F81: 1 | G81: 341.17 | H81: 0.15 | I81: Credit Card | J81: 289.9945
A82: SALE80 | B82: 45885 | C82: CUST1176 | D82: PROD52 | E82: STORE8 | F82: 1 | G82: 442.27 | H82: 0.06 | I82: COD | J82: 415.7338
A83: SALE81 | B83: 45616 | C83: CUST1253 | D83: PROD71 | E83: STORE9 | F83: 1 | G83: 363.73 | H83: 0.25 | I83: PayPal | J83: 272.7975
A84: SALE82 | B84: 45518 | C84: CUST1378 | D84: PROD91 | E84: STORE17 | F84: 2 | G84: 601.33 | H84: 0.16 | I84: PayPal | J84: 1010.2344
A85: SALE83 | B85: 45427 | C85: CUST1403 | D85: PROD17 | E85: STORE18 | F85: 4 | G85: 34.39 | H85: 0.03 | I85: PayPal | J85: 133.4332
A86: SALE84 | B86: 45268 | C86: CUST1423 | D86: PROD46 | E86: STORE17 | F86: 1 | G86: 773.57 | H86: 0.05 | I86: COD
A87: SALE85 | B87: 45282 | C87: CUST1054 | D87: PROD88 | E87: STORE7 | F87: 4 | G87: 127.1 | H87: 0.24 | I87: COD | J87: 386.384
A88: SALE86 | B88: 45545 | C88: CUST1303 | D88: PROD20 | E88: STORE3 | F88: 3 | G88: 899.58 | H88: 0.28 | I88: PayPal | J88: 1943.0928
A89: SALE87 | B89: 45755 | C89: CUST1327 | D89: PROD1 | E89: STORE10 | F89: 3 | G89: 964.39 | H89: 0.04 | I89: Credit Card | J89: 2777.4432
A90: SALE88 | B90: 45588 | C90: CUST1183 | D90: PROD38 | E90: STORE0 | F90: 2 | G90: 217.83 | H90: 0.14 | I90: PayPal | J90: 374.6676
A91: SALE89 | B91: 45848 | C91: CUST1143 | D91: PROD17 | E91: STORE1 | F91: 4 | G91: 187.71 | H91: 0.06 | I91: COD | J91: 705.7896
A92: SALE90 | B92: 45577 | C92: CUST1010 | D92: PROD33 | E92: STORE18 | F92: 2 | G92: 350.12 | H92: 0.12 | I92: COD | J92: 616.2112
A93: SALE91 | B93: 45312 | C93: CUST1406 | D93: PROD16 | E93: STORE1 | F93: 4 | G93: 102.19 | H93: 0.17 | I93: PayPal | J93: 339.2708
A94: SALE92 | B94: 45350 | C94: CUST1007 | D94: PROD86 | E94: STORE4 | F94: 1 | G94: 696.53 | H94: 0.17 | I94: Credit Card | J94: 578.1199
A95: SALE93 | B95: 45657 | C95: CUST1065 | D95: PROD19 | E95: STORE4 | F95: 2 | G95: 327.52 | H95: 0.15 | I95: PayPal | J95: 556.784
A96: SALE94 | B96: 45530 | C96: CUST1298 | D96: PROD97 | E96: STORE19 | F96: 2 | G96: 569.36 | H96: 0.01 | I96: PayPal
A97: SALE95 | B97: 45556 | C97: CUST1321 | D97: PROD99 | E97: STORE6 | F97: 2 | G97: 68.29 | H97: 0.14 | I97: COD | J97: 117.4588
A98: SALE96 | B98: 45523 | C98: CUST1244 | D98: PROD50 | E98: STORE10 | F98: 1 | G98: 842.9 | H98: 0.06 | I98: COD | J98: 792.326
A99: SALE97 | B99: 45587 | C99: CUST1287 | D99: PROD3 | E99: STORE3 | F99: 3 | G99: 751.94 | H99: 0.26 | I99: PayPal | J99: 1669.3068
A100: SALE98 | B100: 45580 | C100: CUST1131 | D100: PROD56 | E100: STORE7 | F100: 4 | G100: 476.28 | H100: 0.17 | I100: Credit Card | J100: 1581.2496
...

Sheet  XLOOKUP VLOOKUP 
A1: Vlookup | L1: Xlookup
A2: Sales_ID | B2: Order_Date | C2: Customer_ID | D2: Product_ID | E2: Store_ID | F2: Quantity | G2: Unit_Price | H2: Discount | I2: Payment_Type | J2: Total_Amount | L2: Sales_ID | M2: Order_Date | N2: Customer_ID | O2: Product_ID | P2: Store_ID | Q2: Quantity | R2: Unit_Price | S2: Discount | T2: Payment_Type | U2: Total_Amount
A3: SALE0 | B3: =IFERROR(VLOOKUP(A3,'f Excel formulas for calculatio'!A:E,2,FALSE)," ") -> 45480 | C3: =IFERROR(VLOOKUP(B3,'f Excel formulas for calculatio'!B:F,2,FALSE),"0") -> CUST1409 | D3: =IFERROR(VLOOKUP(C3,'f Excel formulas for calculatio'!C:G,2,FALSE),"0") -> PROD97 | E3: =IFERROR(VLOOKUP(D3,'f Excel formulas for calculatio'!D:H,2,FALSE),"0") -> STORE3 | F3: =IFERROR(VLOOKUP(E3,'f Excel formulas for calculatio'!E:I,2,FALSE),"0") -> 1 | G3: =IFERROR(VLOOKUP(F3,'f Excel formulas for calculatio'!F:J,2,FALSE),"0") -> 218.04 | H3: =IFERROR(VLOOKUP(G3,'f Excel formulas for calculatio'!G:K,2,FALSE),"0") -> 0.09 | I3: =IFERROR(VLOOKUP(H3,'f Excel formulas for calculatio'!H:L,2,FALSE),"0") -> Credit Card | J3: =IFERROR(VLOOKUP(I3,'f Excel formulas for calculatio'!I:M,2,FALSE),"0") -> 198.4164 | L3: SALE0 | M3: =_xlfn.XLOOKUP(L3,A3,B3) -> 45480 | N3: =_xlfn.XLOOKUP(M3,B3,C3) -> CUST1409 | O3: =_xlfn.XLOOKUP(N3,C3,D3) -> PROD97 | P3: =_xlfn.XLOOKUP(O3,D3,E3) -> STORE3 | Q3: =_xlfn.XLOOKUP(P3,E3,F3) -> 1 | R3: =_xlfn.XLOOKUP(Q3,F3,G3) -> 218.04 | S3: =_xlfn.XLOOKUP(R3,G3,H3) -> 0.09 | T3: =_xlfn.XLOOKUP(S3,H3,I3) -> Credit Card | U3: =_xlfn.XLOOKUP(T3,I3,J3) -> 198.4164
A4: SALE1 | B4: =IFERROR(VLOOKUP(A4,'f Excel formulas for calculatio'!A:E,2,FALSE)," ") -> 45285 | C4: =IFERROR(VLOOKUP(B4,'f Excel formulas for calculatio'!B:F,2,FALSE),"0") -> CUST1467 | D4: =IFERROR(VLOOKUP(C4,'f Excel formulas for calculatio'!C:G,2,FALSE),"0") -> PROD74 | E4: =IFERROR(VLOOKUP(D4,'f Excel formulas for calculatio'!D:H,2,FALSE),"0") -> STORE17 | F4: =IFERROR(VLOOKUP(E4,'f Excel formulas for calculatio'!E:I,2,FALSE),"0") -> 3 | G4: =IFERROR(VLOOKUP(F4,'f Excel formulas for calculatio'!F:J,2,FALSE),"0") -> 104.47 | H4: =IFERROR(VLOOKUP(G4,'f Excel formulas for calculatio'!G:K,2,FALSE),"0") -> 0.27 | I4: =IFERROR(VLOOKUP(H4,'f Excel formulas for calculatio'!H:L,2,FALSE),"0") -> PayPal | J4: =IFERROR(VLOOKUP(I4,'f Excel formulas for calculatio'!I:M,2,FALSE),"0") -> 228.7893 | L4: SALE1 | M4: =_xlfn.XLOOKUP(L4,A4,B4) -> 45285 | N4: =_xlfn.XLOOKUP(M4,B4,C4) -> CUST1467 | O4: =_xlfn.XLOOKUP(N4,C4,D4) -> PROD74 | P4: =_xlfn.XLOOKUP(O4,D4,E4) -> STORE17 | Q4: =_xlfn.XLOOKUP(P4,E4,F4) -> 3 | R4: =_xlfn.XLOOKUP(Q4,F4,G4) -> 104.47 | S4: =_xlfn.XLOOKUP(R4,G4,H4) -> 0.27 | T4: =_xlfn.XLOOKUP(S4,H4,I4) -> PayPal | U4: =_xlfn.XLOOKUP(T4,I4,J4) -> 228.7893
A5: SALE2 | B5: =IFERROR(VLOOKUP(A5,'f Excel formulas for calculatio'!A:E,2,FALSE)," ") -> 45446 | C5: =IFERROR(VLOOKUP(B5,'f Excel formulas for calculatio'!B:F,2,FALSE),"0") -> CUST1056 | D5: =IFERROR(VLOOKUP(C5,'f Excel formulas for calculatio'!C:G,2,FALSE),"0") -> PROD49 | E5: =IFERROR(VLOOKUP(D5,'f Excel formulas for calculatio'!D:H,2,FALSE),"0") -> STORE8 | F5: =IFERROR(VLOOKUP(E5,'f Excel formulas for calculatio'!E:I,2,FALSE),"0") -> 4 | G5: =IFERROR(VLOOKUP(F5,'f Excel formulas for calculatio'!F:J,2,FALSE),"0") -> 914.05 | H5: =IFERROR(VLOOKUP(G5,'f Excel formulas for calculatio'!G:K,2,FALSE),"0") -> 0.25 | I5: =IFERROR(VLOOKUP(H5,'f Excel formulas for calculatio'!H:L,2,FALSE),"0") -> Credit Card | J5: =IFERROR(VLOOKUP(I5,'f Excel formulas for calculatio'!I:M,2,FALSE),"0") -> 198.4164 | L5: SALE2 | M5: =_xlfn.XLOOKUP(L5,A5,B5) -> 45446 | N5: =_xlfn.XLOOKUP(M5,B5,C5) -> CUST1056 | O5: =_xlfn.XLOOKUP(N5,C5,D5) -> PROD49 | P5: =_xlfn.XLOOKUP(O5,D5,E5) -> STORE8 | Q5: =_xlfn.XLOOKUP(P5,E5,F5) -> 4 | R5: =_xlfn.XLOOKUP(Q5,F5,G5) -> 914.05 | S5: =_xlfn.XLOOKUP(R5,G5,H5) -> 0.25 | T5: =_xlfn.XLOOKUP(S5,H5,I5) -> Credit Card | U5: =_xlfn.XLOOKUP(T5,I5,J5) -> 198.4164
A6: SALE3 | B6: =IFERROR(VLOOKUP(A6,'f Excel formulas for calculatio'!A:E,2,FALSE)," ") -> 45259 | C6: =IFERROR(VLOOKUP(B6,'f Excel formulas for calculatio'!B:F,2,FALSE),"0") -> CUST1346 | D6: =IFERROR(VLOOKUP(C6,'f Excel formulas for calculatio'!C:G,2,FALSE),"0") -> PROD76 | E6: =IFERROR(VLOOKUP(D6,'f Excel formulas for calculatio'!D:H,2,FALSE),"0") -> STORE8 | F6: =IFERROR(VLOOKUP(E6,'f Excel formulas for calculatio'!E:I,2,FALSE),"0") -> 4 | G6: =IFERROR(VLOOKUP(F6,'f Excel formulas for calculatio'!F:J,2,FALSE),"0") -> 914.05 | H6: =IFERROR(VLOOKUP(G6,'f Excel formulas for calculatio'!G:K,2,FALSE),"0") -> 0.25 | I6: =IFERROR(VLOOKUP(H6,'f Excel formulas for calculatio'!H:L,2,FALSE),"0") -> Credit Card | J6: =IFERROR(VLOOKUP(I6,'f Excel formulas for calculatio'!I:M,2,FALSE),"0") -> 198.4164 | L6: SALE3 | M6: =_xlfn.XLOOKUP(L6,A6,B6) -> 45259 | N6: =_xlfn.XLOOKUP(M6,B6,C6) -> CUST1346 | O6: =_xlfn.XLOOKUP(N6,C6,D6) -> PROD76 | P6: =_xlfn.XLOOKUP(O6,D6,E6) -> STORE8 | Q6: =_xlfn.XLOOKUP(P6,E6,F6) -> 4 | R6: =_xlfn.XLOOKUP(Q6,F6,G6) -> 914.05 | S6: =_xlfn.XLOOKUP(R6,G6,H6) -> 0.25 | T6: =_xlfn.XLOOKUP(S6,H6,I6) -> Credit Card | U6: =_xlfn.XLOOKUP(T6,I6,J6) -> 198.4164
A7: SALE4 | B7: =IFERROR(VLOOKUP(A7,'f Excel formulas for calculatio'!A:E,2,FALSE)," ") -> 45297 | C7: =IFERROR(VLOOKUP(B7,'f Excel formulas for calculatio'!B:F,2,FALSE),"0") -> CUST1493 | D7: =IFERROR(VLOOKUP(C7,'f Excel formulas for calculatio'!C:G,2,FALSE),"0") -> PROD59 | E7: =IFERROR(VLOOKUP(D7,'f Excel formulas for calculatio'!D:H,2,FALSE),"0") -> STORE5 | F7: =IFERROR(VLOOKUP(E7,'f Excel formulas for calculatio'!E:I,2,FALSE),"0") -> 3 | G7: =IFERROR(VLOOKUP(F7,'f Excel formulas for calculatio'!F:J,2,FALSE),"0") -> 104.47 | H7: =IFERROR(VLOOKUP(G7,'f Excel formulas for calculatio'!G:K,2,FALSE),"0") -> 0.27 | I7: =IFERROR(VLOOKUP(H7,'f Excel formulas for calculatio'!H:L,2,FALSE),"0") -> PayPal | J7: =IFERROR(VLOOKUP(I7,'f Excel formulas for calculatio'!I:M,2,FALSE),"0") -> 228.7893 | L7: SALE4 | M7: =_xlfn.XLOOKUP(L7,A7,B7) -> 45297 | N7: =_xlfn.XLOOKUP(M7,B7,C7) -> CUST1493 | O7: =_xlfn.XLOOKUP(N7,C7,D7) -> PROD59 | P7: =_xlfn.XLOOKUP(O7,D7,E7) -> STORE5 | Q7: =_xlfn.XLOOKUP(P7,E7,F7) -> 3 | R7: =_xlfn.XLOOKUP(Q7,F7,G7) -> 104.47 | S7: =_xlfn.XLOOKUP(R7,G7,H7) -> 0.27 | T7: =_xlfn.XLOOKUP(S7,H7,I7) -> PayPal | U7: =_xlfn.XLOOKUP(T7,I7,J7) -> 228.7893
A8: SALE5 | B8: =IFERROR(VLOOKUP(A8,'f Excel formulas for calculatio'!A:E,2,FALSE)," ") -> 45499 | C8: =IFERROR(VLOOKUP(B8,'f Excel formulas for calculatio'!B:F,2,FALSE),"0") -> CUST1116 | D8: =IFERROR(VLOOKUP(C8,'f Excel formulas for calculatio'!C:G,2,FALSE),"0") -> PROD15 | E8: =IFERROR(VLOOKUP(D8,'f Excel formulas for calculatio'!D:H,2,FALSE),"0") -> STORE7 | F8: =IFERROR(VLOOKUP(E8,'f Excel formulas for calculatio'!E:I,2,FALSE),"0") -> 3 | G8: =IFERROR(VLOOKUP(F8,'f Excel formulas for calculatio'!F:J,2,FALSE),"0") -> 104.47 | H8: =IFERROR(VLOOKUP(G8,'f Excel formulas for calculatio'!G:K,2,FALSE),"0") -> 0.27 | I8: =IFERROR(VLOOKUP(H8,'f Excel formulas for calculatio'!H:L,2,FALSE),"0") -> PayPal | J8: =IFERROR(VLOOKUP(I8,'f Excel formulas for calculatio'!I:M,2,FALSE),"0") -> 228.7893 | L8: SALE5 | M8: =_xlfn.XLOOKUP(L8,A8,B8) -> 45499 | N8: =_xlfn.XLOOKUP(M8,B8,C8) -> CUST1116 | O8: =_xlfn.XLOOKUP(N8,C8,D8) -> PROD15 | P8: =_xlfn.XLOOKUP(O8,D8,E8) -> STORE7 | Q8: =_xlfn.XLOOKUP(P8,E8,F8) -> 3 | R8: =_xlfn.XLOOKUP(Q8,F8,G8) -> 104.47 | S8: =_xlfn.XLOOKUP(R8,G8,H8) -> 0.27 | T8: =_xlfn.XLOOKUP(S8,H8,I8) -> PayPal | U8: =_xlfn.XLOOKUP(T8,I8,J8) -> 228.7893
A9: SALE6 | B9: =IFERROR(VLOOKUP(A9,'f Excel formulas for calculatio'!A:E,2,FALSE)," ") -> 45850 | C9: =IFERROR(VLOOKUP(B9,'f Excel formulas for calculatio'!B:F,2,FALSE),"0") -> CUST1016 | D9: =IFERROR(VLOOKUP(C9,'f Excel formulas for calculatio'!C:G,2,FALSE),"0") -> PROD56 | E9: =IFERROR(VLOOKUP(D9,'f Excel formulas for calculatio'!D:H,2,FALSE),"0") -> STORE4 | F9: =IFERROR(VLOOKUP(E9,'f Excel formulas for calculatio'!E:I,2,FALSE),"0") -> 2 | G9: =IFERROR(VLOOKUP(F9,'f Excel formulas for calculatio'!F:J,2,FALSE),"0") -> 785.31 | H9: =IFERROR(VLOOKUP(G9,'f Excel formulas for calculatio'!G:K,2,FALSE),"0") -> 0.15 | I9: =IFERROR(VLOOKUP(H9,'f Excel formulas for calculatio'!H:L,2,FALSE),"0") -> PayPal | J9: =IFERROR(VLOOKUP(I9,'f Excel formulas for calculatio'!I:M,2,FALSE),"0") -> 228.7893 | L9: SALE6 | M9: =_xlfn.XLOOKUP(L9,A9,B9) -> 45850 | N9: =_xlfn.XLOOKUP(M9,B9,C9) -> CUST1016 | O9: =_xlfn.XLOOKUP(N9,C9,D9) -> PROD56 | P9: =_xlfn.XLOOKUP(O9,D9,E9) -> STORE4 | Q9: =_xlfn.XLOOKUP(P9,E9,F9) -> 2 | R9: =_xlfn.XLOOKUP(Q9,F9,G9) -> 785.31 | S9: =_xlfn.XLOOKUP(R9,G9,H9) -> 0.15 | T9: =_xlfn.XLOOKUP(S9,H9,I9) -> PayPal | U9: =_xlfn.XLOOKUP(T9,I9,J9) -> 228.7893
A10: SALE7 | B10: =IFERROR(VLOOKUP(A10,'f Excel formulas for calculatio'!A:E,2,FALSE)," ") -> 45248 | C10: =IFERROR(VLOOKUP(B10,'f Excel formulas for calculatio'!B:F,2,FALSE),"0") -> CUST1152 | D10: =IFERROR(VLOOKUP(C10,'f Excel formulas for calculatio'!C:G,2,FALSE),"0") -> PROD70 | E10: =IFERROR(VLOOKUP(D10,'f Excel formulas for calculatio'!D:H,2,FALSE),"0") -> STORE8 | F10: =IFERROR(VLOOKUP(E10,'f Excel formulas for calculatio'!E:I,2,FALSE),"0") -> 4 | G10: =IFERROR(VLOOKUP(F10,'f Excel formulas for calculatio'!F:J,2,FALSE),"0") -> 914.05 | H10: =IFERROR(VLOOKUP(G10,'f Excel formulas for calculatio'!G:K,2,FALSE),"0") -> 0.25 | I10: =IFERROR(VLOOKUP(H10,'f Excel formulas for calculatio'!H:L,2,FALSE),"0") -> Credit Card | J10: =IFERROR(VLOOKUP(I10,'f Excel formulas for calculatio'!I:M,2,FALSE),"0") -> 198.4164 | L10: SALE7 | M10: =_xlfn.XLOOKUP(L10,A10,B10) -> 45248 | N10: =_xlfn.XLOOKUP(M10,B10,C10) -> CUST1152 | O10: =_xlfn.XLOOKUP(N10,C10,D10) -> PROD70 | P10: =_xlfn.XLOOKUP(O10,D10,E10) -> STORE8 | Q10: =_xlfn.XLOOKUP(P10,E10,F10) -> 4 | R10: =_xlfn.XLOOKUP(Q10,F10,G10) -> 914.05 | S10: =_xlfn.XLOOKUP(R10,G10,H10) -> 0.25 | T10: =_xlfn.XLOOKUP(S10,H10,I10) -> Credit Card | U10: =_xlfn.XLOOKUP(T10,I10,J10) -> 198.4164
A11: SALE8 | B11: =IFERROR(VLOOKUP(A11,'f Excel formulas for calculatio'!A:E,2,FALSE)," ") -> 45781 | C11: =IFERROR(VLOOKUP(B11,'f Excel formulas for calculatio'!B:F,2,FALSE),"0") -> CUST1187 | D11: =IFERROR(VLOOKUP(C11,'f Excel formulas for calculatio'!C:G,2,FALSE),"0") -> PROD99 | E11: =IFERROR(VLOOKUP(D11,'f Excel formulas for calculatio'!D:H,2,FALSE),"0") -> STORE5 | F11: =IFERROR(VLOOKUP(E11,'f Excel formulas for calculatio'!E:I,2,FALSE),"0") -> 3 | G11: =IFERROR(VLOOKUP(F11,'f Excel formulas for calculatio'!F:J,2,FALSE),"0") -> 104.47 | H11: =IFERROR(VLOOKUP(G11,'f Excel formulas for calculatio'!G:K,2,FALSE),"0") -> 0.27 | I11: =IFERROR(VLOOKUP(H11,'f Excel formulas for calculatio'!H:L,2,FALSE),"0") -> PayPal | J11: =IFERROR(VLOOKUP(I11,'f Excel formulas for calculatio'!I:M,2,FALSE),"0") -> 228.7893 | L11: SALE8 | M11: =_xlfn.XLOOKUP(L11,A11,B11) -> 45781 | N11: =_xlfn.XLOOKUP(M11,B11,C11) -> CUST1187 | O11: =_xlfn.XLOOKUP(N11,C11,D11) -> PROD99 | P11: =_xlfn.XLOOKUP(O11,D11,E11) -> STORE5 | Q11: =_xlfn.XLOOKUP(P11,E11,F11) -> 3 | R11: =_xlfn.XLOOKUP(Q11,F11,G11) -> 104.47 | S11: =_xlfn.XLOOKUP(R11,G11,H11) -> 0.27 | T11: =_xlfn.XLOOKUP(S11,H11,I11) -> PayPal | U11: =_xlfn.XLOOKUP(T11,I11,J11) -> 228.7893
A12: SALE9 | B12: =IFERROR(VLOOKUP(A12,'f Excel formulas for calculatio'!A:E,2,FALSE)," ") -> 45869 | C12: =IFERROR(VLOOKUP(B12,'f Excel formulas for calculatio'!B:F,2,FALSE),"0") -> CUST1464 | D12: =IFERROR(VLOOKUP(C12,'f Excel formulas for calculatio'!C:G,2,FALSE),"0") -> PROD33 | E12: =IFERROR(VLOOKUP(D12,'f Excel formulas for calculatio'!D:H,2,FALSE),"0") -> STORE0 | F12: =IFERROR(VLOOKUP(E12,'f Excel formulas for calculatio'!E:I,2,FALSE),"0") -> 2 | G12: =IFERROR(VLOOKUP(F12,'f Excel formulas for calculatio'!F:J,2,FALSE),"0") -> 785.31 | H12: =IFERROR(VLOOKUP(G12,'f Excel formulas for calculatio'!G:K,2,FALSE),"0") -> 0.15 | I12: =IFERROR(VLOOKUP(H12,'f Excel formulas for calculatio'!H:L,2,FALSE),"0") -> PayPal | J12: =IFERROR(VLOOKUP(I12,'f Excel formulas for calculatio'!I:M,2,FALSE),"0") -> 228.7893 | L12: SALE9 | M12: =_xlfn.XLOOKUP(L12,A12,B12) -> 45869 | N12: =_xlfn.XLOOKUP(M12,B12,C12) -> CUST1464 | O12: =_xlfn.XLOOKUP(N12,C12,D12) -> PROD33 | P12: =_xlfn.XLOOKUP(O12,D12,E12) -> STORE0 | Q12: =_xlfn.XLOOKUP(P12,E12,F12) -> 2 | R12: =_xlfn.XLOOKUP(Q12,F12,G12) -> 785.31 | S12: =_xlfn.XLOOKUP(R12,G12,H12) -> 0.15 | T12: =_xlfn.XLOOKUP(S12,H12,I12) -> PayPal | U12: =_xlfn.XLOOKUP(T12,I12,J12) -> 228.7893
A13: SALE10 | B13: =IFERROR(VLOOKUP(A13,'f Excel formulas for calculatio'!A:E,2,FALSE)," ") -> 45335 | C13: =IFERROR(VLOOKUP(B13,'f Excel formulas for calculatio'!B:F,2,FALSE),"0") -> CUST1065 | D13: =IFERROR(VLOOKUP(C13,'f Excel formulas for calculatio'!C:G,2,FALSE),"0") -> PROD24 | E13: =IFERROR(VLOOKUP(D13,'f Excel formulas for calculatio'!D:H,2,FALSE),"0") -> STORE14 | F13: =IFERROR(VLOOKUP(E13,'f Excel formulas for calculatio'!E:I,2,FALSE),"0") -> 1 | G13: =IFERROR(VLOOKUP(F13,'f Excel formulas for calculatio'!F:J,2,FALSE),"0") -> 218.04 | H13: =IFERROR(VLOOKUP(G13,'f Excel formulas for calculatio'!G:K,2,FALSE),"0") -> 0.09 | I13: =IFERROR(VLOOKUP(H13,'f Excel formulas for calculatio'!H:L,2,FALSE),"0") -> Credit Card | J13: =IFERROR(VLOOKUP(I13,'f Excel formulas for calculatio'!I:M,2,FALSE),"0") -> 198.4164 | L13: SALE10 | M13: =_xlfn.XLOOKUP(L13,A13,B13) -> 45335 | N13: =_xlfn.XLOOKUP(M13,B13,C13) -> CUST1065 | O13: =_xlfn.XLOOKUP(N13,C13,D13) -> PROD24 | P13: =_xlfn.XLOOKUP(O13,D13,E13) -> STORE14 | Q13: =_xlfn.XLOOKUP(P13,E13,F13) -> 1 | R13: =_xlfn.XLOOKUP(Q13,F13,G13) -> 218.04 | S13: =_xlfn.XLOOKUP(R13,G13,H13) -> 0.09 | T13: =_xlfn.XLOOKUP(S13,H13,I13) -> Credit Card | U13: =_xlfn.XLOOKUP(T13,I13,J13) -> 198.4164
A14: SALE11 | B14: =IFERROR(VLOOKUP(A14,'f Excel formulas for calculatio'!A:E,2,FALSE)," ") -> 45801 | C14: =IFERROR(VLOOKUP(B14,'f Excel formulas for calculatio'!B:F,2,FALSE),"0") -> CUST1320 | D14: =IFERROR(VLOOKUP(C14,'f Excel formulas for calculatio'!C:G,2,FALSE),"0") -> PROD39 | E14: =IFERROR(VLOOKUP(D14,'f Excel formulas for calculatio'!D:H,2,FALSE),"0") -> STORE1 | F14: =IFERROR(VLOOKUP(E14,'f Excel formulas for calculatio'!E:I,2,FALSE),"0") -> 4 | G14: =IFERROR(VLOOKUP(F14,'f Excel formulas for calculatio'!F:J,2,FALSE),"0") -> 914.05 | H14: =IFERROR(VLOOKUP(G14,'f Excel formulas for calculatio'!G:K,2,FALSE),"0") -> 0.25 | I14: =IFERROR(VLOOKUP(H14,'f Excel formulas for calculatio'!H:L,2,FALSE),"0") -> Credit Card | J14: =IFERROR(VLOOKUP(I14,'f Excel formulas for calculatio'!I:M,2,FALSE),"0") -> 198.4164 | L14: SALE11 | M14: =_xlfn.XLOOKUP(L14,A14,B14) -> 45801 | N14: =_xlfn.XLOOKUP(M14,B14,C14) -> CUST1320 | O14: =_xlfn.XLOOKUP(N14,C14,D14) -> PROD39 | P14: =_xlfn.XLOOKUP(O14,D14,E14) -> STORE1 | Q14: =_xlfn.XLOOKUP(P14,E14,F14) -> 4 | R14: =_xlfn.XLOOKUP(Q14,F14,G14) -> 914.05 | S14: =_xlfn.XLOOKUP(R14,G14,H14) -> 0.25 | T14: =_xlfn.XLOOKUP(S14,H14,I14) -> Credit Card | U14: =_xlfn.XLOOKUP(T14,I14,J14) -> 198.4164
... A2002: SALE1999 | B2002: =IFERROR(VLOOKUP(A2002,'f Excel formulas for calculatio'!A:E,2,FALSE)," ") -> 45267 | C2002: =IFERROR(VLOOKUP(B2002,'f Excel formulas for calculatio'!B:F,2,FALSE),"0") -> CUST1344 | D2002: =IFERROR(VLOOKUP(C2002,'f Excel formulas for calculatio'!C:G,2,FALSE),"0") -> PROD79 | E2002: =IFERROR(VLOOKUP(D2002,'f Excel formulas for calculatio'!D:H,2,FALSE),"0") -> STORE1 | F2002: =IFERROR(VLOOKUP(E2002,'f Excel formulas for calculatio'!E:I,2,FALSE),"0") -> 4 | G2002: =IFERROR(VLOOKUP(F2002,'f Excel formulas for calculatio'!F:J,2,FALSE),"0") -> 914.05 | H2002: =IFERROR(VLOOKUP(G2002,'f Excel formulas for calculatio'!G:K,2,FALSE),"0") -> 0.25 | I2002: =IFERROR(VLOOKUP(H2002,'f Excel formulas for calculatio'!H:L,2,FALSE),"0") -> Credit Card | J2002: =IFERROR(VLOOKUP(I2002,'f Excel formulas for calculatio'!I:M,2,FALSE),"0") -> 198.4164 | L2002: SALE1999 | M2002: =_xlfn.XLOOKUP(L2002,A2002,B2002) -> 45267 | N2002: =_xlfn.XLOOKUP(M2002,B2002,C2002) -> CUST1344 | O2002: =_xlfn.XLOOKUP(N2002,C2002,D2002) -> PROD79 | P2002: =_xlfn.XLOOKUP(O2002,D2002,E2002) -> STORE1 | Q2002: =_xlfn.XLOOKUP(P2002,E2002,F2002) -> 4 | R2002: =_xlfn.XLOOKUP(Q2002,F2002,G2002) -> 914.05 | S2002: =_xlfn.XLOOKUP(R2002,G2002,H2002) -> 0.25 | T2002: =_xlfn.XLOOKUP(S2002,H2002,I2002) -> Credit Card | U2002: =_xlfn.XLOOKUP(T2002,I2002,J2002) -> 198.4164

Sheet pivot table
A1: Row Labels | B1: Sum of Total_Amount | C1: Sum of Quantity | D1: Sum of Discount
A2: COD | B2: 701525.29 | C2: 1642 | D2: 98.03
A3: Credit Card | B3: 713754.93 | C3: 1614 | D3: 96.73
A4: PayPal | B4: 755627.24 | C4: 1692 | D4: 100.82
A5: Grand Total | B5: 2170907.5 | C5: 4948 | D5: 295.58

Sheet Descriptive statistics
A1: Sales_ID | B1: Order_Date | C1: Customer_ID | D1: Product_ID | E1: Store_ID | F1: Quantity | G1: Unit_Price | H1: Discount | I1: Payment_Type | J1: Total_Amount
A2: SALE0 | B2: 45480 | C2: CUST1409 | D2: PROD97 | E2: STORE3 | F2: 1 | G2: 218.04 | H2: 0.09 | I2: Credit Card | J2: 198.4164 | L2: Quantity | O2: Total_Amount
A3: SALE1 | B3: 45285 | C3: CUST1467 | D3: PROD74 | E3: STORE17 | F3: 3 | G3: 104.47 | H3: 0.27 | I3: PayPal | J3: 228.7893
A4: SALE2 | B4: 45446 | C4: CUST1056 | D4: PROD49 | E4: STORE8 | F4: 4 | G4: 914.05 | H4: 0.25 | I4: Credit Card | J4: 2742.15 | L4: Mean | M4: 2.4802005 | O4: Mean | P4: 1087.629
A5: SALE3 | B5: 45259 | C5: CUST1346 | D5: PROD76 | E5: STORE8 | F5: 1 | G5: 921.51 | H5: 0.16 | I5: COD | J5: 774.0684 | L5: Standard Error | M5: 0.024897726 | O5: Standard Error | P5: 18.356936
A6: SALE4 | B6: 45297 | C6: CUST1493 | D6: PROD59 | E6: STORE5 | F6: 3 | G6: 745.3 | H6: 0.18 | I6: Credit Card | J6: 1833.438 | L6: Median | M6: 2 | O6: Median | P6: 868.7182
A7: SALE5 | B7: 45499 | C7: CUST1116 | D7: PROD15 | E7: STORE7 | F7: 3 | G7: 147.01 | H7: 0.19 | I7: COD | J7: 357.2343 | L7: Mode | M7: 2 | O7: Mode | P7: #N/A
A8: SALE6 | B8: 45850 | C8: CUST1016 | D8: PROD56 | E8: STORE4 | F8: 2 | G8: 785.31 | H8: 0.15 | I8: PayPal | J8: 1335.027 | L8: Standard Deviation | M8: 1.1120675 | O8: Standard Deviation | P8: 820.12576
A9: SALE7 | B9: 45248 | C9: CUST1152 | D9: PROD70 | E9: STORE8 | F9: 4 | G9: 342.39 | H9: 0.23 | I9: PayPal | J9: 1054.5612 | L9: Sample Variance | M9: 1.236694 | O9: Sample Variance | P9: 672606.27
A10: SALE8 | B10: 45781 | C10: CUST1187 | D10: PROD99 | E10: STORE5 | G10: 448.25 | H10: 0.07 | I10: PayPal | J10: 1250.6175 | L10: Kurtosis | M10: -1.3454153 | O10: Kurtosis | P10: 0.041826531
A11: SALE9 | B11: 45869 | C11: CUST1464 | D11: PROD33 | E11: STORE0 | F11: 2 | G11: 873.17 | H11: 0.23 | I11: PayPal | J11: 1344.6818 | L11: Skewness | M11: 0.025776009 | O11: Skewness | P11: 0.87824016
A12: SALE10 | B12: 45335 | C12: CUST1065 | D12: PROD24 | E12: STORE14 | F12: 1 | G12: 278.63 | H12: 0.07 | I12: Credit Card | J12: 259.1259 | L12: Range | M12: 3 | O12: Range | P12: 3889.7838
A13: SALE11 | B13: 45801 | C13: CUST1320 | D13: PROD39 | E13: STORE1 | F13: 4 | G13: 286.92 | H13: 0.17 | I13: Credit Card | J13: 952.5744 | L13: Minimum | M13: 1 | O13: Minimum | P13: 18.459
A14: SALE12 | B14: 45528 | C14: CUST1237 | D14: PROD88 | E14: STORE4 | F14: 4 | G14: 644.58 | H14: 0.01 | I14: Credit Card | J14: 2552.5368 | L14: Maximum | M14: 4 | O14: Maximum | P14: 3908.2428
A15: SALE13 | B15: 45875 | C15: CUST1443 | D15: PROD34 | E15: STORE16 | F15: 2 | G15: 316.9 | H15: 0.3 | I15: PayPal | J15: 443.66 | L15: Sum | M15: 4948 | O15: Sum | P15: 2170907.5
A16: SALE14 | B16: 45829 | C16: CUST1348 | D16: PROD24 | E16: STORE15 | F16: 4 | G16: 403.47 | H16: 0.29 | I16: PayPal | J16: 1145.8548 | L16: Count | M16: 1995 | O16: Count | P16: 1996
A17: SALE15 | B17: 45636 | C17: CUST1435 | D17: PROD36 | E17: STORE9 | G17: 871.34 | H17: 0.04 | I17: COD | J17: 2509.4592
A18: SALE16 | B18: 45913 | C18: CUST1276 | D18: PROD65 | E18: STORE19 | F18: 2 | G18: 451.98 | H18: 0.25 | I18: Credit Card | J18: 677.97 | L18: Unit_Price
A19: SALE17 | B19: 45637 | C19: CUST1079 | D19: PROD27 | E19: STORE4 | F19: 2 | G19: 502.69 | H19: 0.23 | I19: Credit Card | J19: 774.1426
A20: SALE18 | B20: 45517 | C20: CUST1094 | D20: PROD39 | E20: STORE4 | F20: 2 | G20: 559.23 | H20: 0.25 | I20: COD | J20: 838.845 | L20: Mean | M20: 513.98477
A21: SALE19 | B21: 45369 | C21: CUST1239 | D21: PROD60 | E21: STORE13 | F21: 4 | H21: 0.04 | I21: COD | J21: 1782.4512 | L21: Standard Error | M21: 6.3172736
A22: SALE20 | B22: 45843 | C22: CUST1144 | D22: PROD72 | E22: STORE17 | F22: 3 | G22: 986.04 | H22: 0.27 | I22: COD | J22: 2159.4276 | L22: Median | M22: 522.72
A23: SALE21 | B23: 45447 | C23: CUST1396 | D23: PROD43 | E23: STORE18 | F23: 1 | G23: 589.56 | H23: 0.22 | I23: Credit Card | J23: 459.8568 | L23: Mode | M23: 871.34
A24: SALE22 | B24: 45394 | C24: CUST1476 | D24: PROD69 | E24: STORE10 | F24: 3 | G24: 979.42 | H24: 0.03 | I24: PayPal | J24: 2850.1122 | L24: Standard Deviation | M24: 282.3051
A25: SALE23 | B25: 45466 | C25: CUST1368 | D25: PROD12 | E25: STORE8 | F25: 1 | G25: 719.28 | H25: 0.08 | I25: Credit Card | J25: 661.7376 | L25: Sample Variance | M25: 79696.168
A26: SALE24 | B26: 45908 | C26: CUST1186 | D26: PROD67 | E26: STORE6 | F26: 3 | G26: 77.6 | H26: 0.07 | I26: Credit Card | J26: 216.504 | L26: Kurtosis | M26: -1.1924285
A27: SALE25 | B27: 45552 | C27: CUST1381 | D27: PROD5 | E27: STORE3 | F27: 4 | G27: 852.71 | H27: 0.14 | I27: PayPal | J27: 2933.3224 | L27: Skewness | M27: -0.036741245
A28: SALE26 | B28: 45294 | C28: CUST1213 | D28: PROD98 | E28: STORE8 | F28: 4 | G28: 156.16 | I28: Credit Card | J28: 599.6544 | L28: Range | M28: 979.8
A29: SALE27 | B29: 45710 | C29: CUST1200 | D29: PROD77 | E29: STORE8 | F29: 3 | G29: 815.49 | H29: 0.17 | I29: Credit Card | J29: 2030.5701 | L29: Minimum | M29: 20.09
A30: SALE28 | B30: 45923 | C30: CUST1148 | D30: PROD13 | E30: STORE2 | F30: 2 | G30: 74.21 | H30: 0.11 | I30: PayPal | J30: 132.0938 | L30: Maximum | M30: 999.89
A31: SALE29 | B31: 45302 | C31: CUST1348 | D31: PROD99 | E31: STORE3 | G31: 451.67 | H31: 0.15 | I31: Credit Card | J31: 1535.678 | L31: Sum | M31: 1026427.6
A32: SALE30 | B32: 45217 | C32: CUST1028 | D32: PROD5 | E32: STORE19 | F32: 1 | G32: 429.38 | H32: 0.13 | I32: PayPal | J32: 373.5606 | L32: Count | M32: 1997
A33: SALE31 | B33: 45593 | C33: CUST1412 | D33: PROD53 | E33: STORE12 | F33: 2 | G33: 148.96 | H33: 0.03 | I33: COD | J33: 288.9824
A34: SALE32 | B34: 45597 | C34: CUST1398 | D34: PROD75 | E34: STORE8 | F34: 4 | G34: 313.83 | H34: 0.08 | I34: Credit Card | J34: 1154.8944
A35: SALE33 | B35: 45620 | C35: CUST1453 | D35: PROD12 | E35: STORE6 | F35: 2 | G35: 717.31 | H35: 0.15 | I35: Credit Card | J35: 1219.427
A36: SALE34 | B36: 45215 | C36: CUST1344 | D36: PROD79 | E36: STORE1 | G36: 873.22 | H36: 0.18 | I36: Credit Card | J36: 2148.1212
A37: SALE35 | B37: 45878 | C37: CUST1218 | D37: PROD16 | E37: STORE3 | F37: 4 | G37: 109.36 | H37: 0.19 | I37: COD | J37: 354.3264
A38: SALE36 | B38: 45635 | C38: CUST1086 | D38: PROD5 | E38: STORE7 | F38: 3 | G38: 559.52 | H38: 0.16 | I38: PayPal | J38: 1409.9904
A39: SALE37 | B39: 45329 | C39: CUST1492 | D39: PROD10 | E39: STORE17 | F39: 3 | G39: 121.76 | H39: 0.27 | I39: PayPal | J39: 266.6544
A40: SALE38 | B40: 45378 | C40: CUST1189 | D40: PROD33 | E40: STORE13 | F40: 4 | G40: 735.32 | H40: 0.06 | I40: COD | J40: 2764.8032
A41: SALE39 | B41: 45264 | C41: CUST1431 | D41: PROD94 | E41: STORE3 | F41: 2 | G41: 600.73 | H41: 0.08 | I41: Credit Card | J41: 1105.3432
A42: SALE40 | B42: 45486 | C42: CUST1072 | D42: PROD26 | E42: STORE19 | F42: 2 | G42: 873.86 | H42: 0.07 | I42: COD | J42: 1625.3796
A43: SALE41 | B43: 45241 | C43: CUST1302 | D43: PROD23 | E43: STORE8 | F43: 3 | G43: 342.47 | H43: 0.08 | I43: PayPal | J43: 945.2172
A44: SALE42 | B44: 45649 | C44: CUST1335 | D44: PROD29 | E44: STORE9 | F44: 2 | G44: 915.15 | H44: 0.16 | I44: PayPal | J44: 1537.452
A45: SALE43 | B45: 45677 | C45: CUST1084 | D45: PROD33 | E45: STORE17 | G45: 863.11 | H45: 0.28 | I45: PayPal | J45: 1864.3176
A46: SALE44 | B46: 45538 | C46: CUST1203 | D46: PROD43 | E46: STORE12 | F46: 2 | G46: 209.32 | H46: 0.23 | I46: COD | J46: 322.3528
A47: SALE45 | B47: 45606 | C47: CUST1470 | D47: PROD59 | E47: STORE8 | F47: 4 | G47: 288.6 | H47: 0.09 | I47: PayPal | J47: 1050.504
A48: SALE46 | B48: 45570 | C48: CUST1070 | D48: PROD78 | E48: STORE16 | F48: 1 | G48: 418.69 | H48: 0.06 | I48: PayPal | J48: 393.5686
A49: SALE47 | B49: 45466 | C49: CUST1008 | D49: PROD30 | E49: STORE11 | F49: 1 | G49: 135.78 | H49: 0.14 | I49: PayPal | J49: 116.7708
A50: SALE48 | B50: 45218 | C50: CUST1203 | D50: PROD44 | E50: STORE17 | F50: 1 | G50: 517.13 | H50: 0.28 | I50: Credit Card | J50: 372.3336
A51: SALE49 | B51: 45607 | C51: CUST1420 | D51: PROD21 | E51: STORE16 | F51: 2 | G51: 384.66 | H51: 0.08 | I51: COD | J51: 707.7744
A52: SALE50 | B52: 45291 | C52: CUST1070 | D52: PROD52 | E52: STORE9 | F52: 3 | G52: 83.7 | H52: 0.24 | I52: PayPal | J52: 190.836
A53: SALE51 | B53: 45689 | C53: CUST1142 | D53: PROD69 | E53: STORE7 | F53: 3 | G53: 76.57 | H53: 0.26 | I53: Credit Card | J53: 169.9854
A54: SALE52 | B54: 45894 | C54: CUST1148 | D54: PROD89 | E54: STORE6 | F54: 3 | I54: Credit Card | J54: 486.0633
A55: SALE53 | B55: 45677 | C55: CUST1324 | D55: PROD20 | E55: STORE8 | F55: 1 | G55: 900.35 | H55: 0.13 | I55: COD | J55: 783.3045
A56: SALE54 | B56: 45706 | C56: CUST1095 | D56: PROD40 | E56: STORE10 | F56: 4 | G56: 428.09 | H56: 0.07 | I56: Credit Card | J56: 1592.4948
A57: SALE55 | B57: 45589 | C57: CUST1416 | D57: PROD49 | E57: STORE11 | F57: 2 | G57: 559.71 | H57: 0.3 | I57: COD | J57: 783.594
A58: SALE56 | B58: 45282 | C58: CUST1080 | D58: PROD34 | E58: STORE6 | F58: 2 | G58: 833.7 | H58: 0.06 | I58: PayPal | J58: 1567.356
A59: SALE57 | B59: 45462 | C59: CUST1467 | D59: PROD47 | E59: STORE14 | F59: 2 | G59: 680.16 | H59: 0.28 | I59: Credit Card | J59: 979.4304
A60: SALE58 | B60: 45633 | C60: CUST1404 | D60: PROD15 | E60: STORE7 | F60: 4 | G60: 733.42 | I60: PayPal | J60: 2552.3016
A61: SALE59 | B61: 45257 | C61: CUST1367 | D61: PROD89 | E61: STORE11 | F61: 1 | G61: 996.33 | H61: 0.23 | I61: PayPal | J61: 767.1741
A62: SALE60 | B62: 45854 | C62: CUST1408 | D62: PROD31 | E62: STORE10 | F62: 1 | G62: 198.83 | H62: 0.09 | I62: COD | J62: 180.9353
A63: SALE61 | B63: 45716 | C63: CUST1239 | D63: PROD19 | E63: STORE7 | F63: 1 | G63: 374.92 | H63: 0.18 | I63: PayPal | J63: 307.4344
A64: SALE62 | B64: 45515 | C64: CUST1464 | D64: PROD93 | E64: STORE16 | F64: 1 | G64: 468.94 | H64: 0.12 | I64: Credit Card | J64: 412.6672
A65: SALE63 | B65: 45927 | C65: CUST1126 | D65: PROD89 | E65: STORE12 | F65: 2 | G65: 121.37 | H65: 0.05 | I65: Credit Card | J65: 230.603
A66: SALE64 | B66: 45914 | C66: CUST1255 | D66: PROD53 | E66: STORE10 | F66: 3 | G66: 480.06 | H66: 0.01 | I66: Credit Card
A67: SALE65 | B67: 45290 | C67: CUST1162 | D67: PROD99 | E67: STORE17 | F67: 2 | G67: 856.57 | H67: 0.24 | I67: Credit Card | J67: 1301.9864
A68: SALE66 | B68: 45213 | C68: CUST1269 | D68: PROD77 | E68: STORE2 | F68: 4 | G68: 814.25 | H68: 0.18 | I68: Credit Card | J68: 2670.74
A69: SALE67 | B69: 45255 | C69: CUST1483 | D69: PROD12 | E69: STORE2 | F69: 1 | G69: 989.17 | H69: 0.2 | I69: PayPal | J69: 791.336
A70: SALE68 | B70: 45270 | C70: CUST1372 | D70: PROD72 | E70: STORE10 | F70: 4 | G70: 62.48 | H70: 0.18 | I70: Credit Card | J70: 204.9344
A71: SALE69 | B71: 45897 | C71: CUST1423 | D71: PROD13 | E71: STORE16 | F71: 4 | G71: 561.24 | H71: 0.24 | I71: Credit Card | J71: 1706.1696
A72: SALE70 | B72: 45849 | C72: CUST1058 | D72: PROD60 | E72: STORE5 | F72: 3 | G72: 92.24 | H72: 0.28 | I72: COD
A73: SALE71 | B73: 45889 | C73: CUST1168 | D73: PROD72 | E73: STORE1 | F73: 2 | G73: 668.3 | H73: 0.07 | I73: Credit Card | J73: 1243.038
A74: SALE72 | B74: 45533 | C74: CUST1409 | D74: PROD38 | E74: STORE5 | F74: 1 | G74: 553.82 | H74: 0.09 | I74: Credit Card | J74: 503.9762
A75: SALE73 | B75: 45626 | C75: CUST1037 | D75: PROD45 | E75: STORE11 | F75: 2 | G75: 556.43 | H75: 0.13 | I75: Credit Card | J75: 968.1882
A76: SALE74 | B76: 45942 | C76: CUST1273 | D76: PROD20 | E76: STORE8 | F76: 1 | G76: 184.98 | H76: 0.1 | I76: COD | J76: 166.482
A77: SALE75 | B77: 45500 | C77: CUST1035 | D77: PROD97 | E77: STORE12 | F77: 4 | G77: 700.18 | H77: 0.23 | I77: Credit Card | J77: 2156.5544
A78: SALE76 | B78: 45285 | C78: CUST1019 | D78: PROD76 | E78: STORE10 | F78: 2 | G78: 686.31 | H78: 0.25 | I78: Credit Card | J78: 1029.465
A79: SALE77 | B79: 45800 | C79: CUST1007 | D79: PROD67 | E79: STORE15 | F79: 1 | G79: 687.82 | H79: 0.27 | I79: COD | J79: 502.1086
A80: SALE78 | B80: 45609 | C80: CUST1221 | D80: PROD83 | E80: STORE8 | F80: 2 | G80: 900.55 | H80: 0.16 | I80: Credit Card | J80: 1512.924
A81: SALE79 | B81: 45268 | C81: CUST1115 | D81: PROD21 | E81: STORE2 | F81: 1 | G81: 341.17 | H81: 0.15 | I81: Credit Card | J81: 289.9945
A82: SALE80 | B82: 45885 | C82: CUST1176 | D82: PROD52 | E82: STORE8 | F82: 1 | G82: 442.27 | H82: 0.06 | I82: COD | J82: 415.7338
A83: SALE81 | B83: 45616 | C83: CUST1253 | D83: PROD71 | E83: STORE9 | F83: 1 | G83: 363.73 | H83: 0.25 | I83: PayPal | J83: 272.7975
A84: SALE82 | B84: 45518 | C84: CUST1378 | D84: PROD91 | E84: STORE17 | F84: 2 | G84: 601.33 | H84: 0.16 | I84: PayPal | J84: 1010.2344
A85: SALE83 | B85: 45427 | C85: CUST1403 | D85: PROD17 | E85: STORE18 | F85: 4 | G85: 34.39 | H85: 0.03 | I85: PayPal | J85: 133.4332
A86: SALE84 | B86: 45268 | C86: CUST1423 | D86: PROD46 | E86: STORE17 | F86: 1 | G86: 773.57 | H86: 0.05 | I86: COD
A87: SALE85 | B87: 45282 | C87: CUST1054 | D87: PROD88 | E87: STORE7 | F87: 4 | G87: 127.1 | H87: 0.24 | I87: COD | J87: 386.384
A88: SALE86 | B88: 45545 | C88: CUST1303 | D88: PROD20 | E88: STORE3 | F88: 3 | G88: 899.58 | H88: 0.28 | I88: PayPal | J88: 1943.0928
A89: SALE87 | B89: 45755 | C89: CUST1327 | D89: PROD1 | E89: STORE10 | F89: 3 | G89: 964.39 | H89: 0.04 | I89: Credit Card | J89: 2777.4432
A90: SALE88 | B90: 45588 | C90: CUST1183 | D90: PROD38 | E90: STORE0 | F90: 2 | G90: 217.83 | H90: 0.14 | I90: PayPal | J90: 374.6676
A91: SALE89 | B91: 45848 | C91: CUST1143 | D91: PROD17 | E91: STORE1 | F91: 4 | G91: 187.71 | H91: 0.06 | I91: COD | J91: 705.7896
A92: SALE90 | B92: 45577 | C92: CUST1010 | D92: PROD33 | E92: STORE18 | F92: 2 | G92: 350.12 | H92: 0.12 | I92: COD | J92: 616.2112
A93: SALE91 | B93: 45312 | C93: CUST1406 | D93: PROD16 | E93: STORE1 | F93: 4 | G93: 102.19 | H93: 0.17 | I93: PayPal | J93: 339.2708
A94: SALE92 | B94: 45350 | C94: CUST1007 | D94: PROD86 | E94: STORE4 | F94: 1 | G94: 696.53 | H94: 0.17 | I94: Credit Card | J94: 578.1199
A95: SALE93 | B95: 45657 | C95: CUST1065 | D95: PROD19 | E95: STORE4 | F95: 2 | G95: 327.52 | H95: 0.15 | I95: PayPal | J95: 556.784
A96: SALE94 | B96: 45530 | C96: CUST1298 | D96: PROD97 | E96: STORE19 | F96: 2 | G96: 569.36 | H96: 0.01 | I96: PayPal
A97: SALE95 | B97: 45556 | C97: CUST1321 | D97: PROD99 | E97: STORE6 | F97: 2 | G97: 68.29 | H97: 0.14 | I97: COD | J97: 117.4588
A98: SALE96 | B98: 45523 | C98: CUST1244 | D98: PROD50 | E98: STORE10 | F98: 1 | G98: 842.9 | H98: 0.06 | I98: COD | J98: 792.326
A99: SALE97 | B99: 45587 | C99: CUST1287 | D99: PROD3 | E99: STORE3 | F99: 3 | G99: 751.94 | H99: 0.26 | I99: PayPal | J99: 1669.3068
A100: SALE98 | B100: 45580 | C100: CUST1131 | D100: PROD56 | E100: STORE7 | F100: 4 | G100: 476.28 | H100: 0.17 | I100: Credit Card | J100: 1581.2496
...

Sheet ●Data visualization
